{
  "associatedLayout": "aventure_NEW",
  "name": "fondcreator",
  "instances": [
    {
      "angle": 0,
      "customSize": true,
      "height": 700,
      "layer": "",
      "locked": true,
      "name": "blackscreen_1280_1",
      "persistentUuid": "7241bfe9-b877-42d7-b5c8-652869cf3e59",
      "width": 1300,
      "x": -1300,
      "y": -700,
      "zOrder": 1003,
      "numberProperties": [
        {
          "name": "animation",
          "value": 0
        }
      ],
      "stringProperties": [],
      "initialVariables": []
    },
    {
      "angle": 0,
      "customSize": true,
      "height": 700,
      "layer": "",
      "locked": true,
      "name": "blackscreen_1280_2",
      "persistentUuid": "b56f1d54-1926-43c5-bd2d-4b7427ad6cc4",
      "width": 1300,
      "x": 0,
      "y": -700,
      "zOrder": 997,
      "numberProperties": [],
      "stringProperties": [],
      "initialVariables": []
    },
    {
      "angle": 0,
      "customSize": true,
      "height": 700,
      "layer": "",
      "locked": true,
      "name": "blackscreen_1280_3",
      "persistentUuid": "a02d2043-ea03-4613-99b7-f0528bb1b8a3",
      "width": 1300,
      "x": 1300,
      "y": -700,
      "zOrder": 1000,
      "numberProperties": [],
      "stringProperties": [],
      "initialVariables": []
    },
    {
      "angle": 0,
      "customSize": true,
      "height": 700,
      "layer": "",
      "locked": true,
      "name": "blackscreen_1280_4",
      "persistentUuid": "c8cfb3f5-5468-4346-adec-dc570dcfbf85",
      "width": 1300,
      "x": -1300,
      "y": 0,
      "zOrder": 1000,
      "numberProperties": [],
      "stringProperties": [],
      "initialVariables": []
    },
    {
      "angle": 0,
      "customSize": true,
      "height": 700,
      "layer": "",
      "locked": true,
      "name": "blackscreen_1280_5",
      "persistentUuid": "0c0f52d9-544b-4e4b-bf8e-065e649a9cd4",
      "width": 1300,
      "x": 0,
      "y": 0,
      "zOrder": 1000,
      "numberProperties": [],
      "stringProperties": [],
      "initialVariables": []
    },
    {
      "angle": 0,
      "customSize": true,
      "height": 700,
      "layer": "",
      "locked": true,
      "name": "blackscreen_1280_6",
      "persistentUuid": "4d6ab86e-1a0d-404d-80b6-f041c309b507",
      "width": 1300,
      "x": 1300,
      "y": 0,
      "zOrder": 1000,
      "numberProperties": [],
      "stringProperties": [],
      "initialVariables": []
    },
    {
      "angle": 0,
      "customSize": true,
      "height": 700,
      "layer": "",
      "locked": true,
      "name": "blackscreen_1280_7",
      "persistentUuid": "2598c933-82de-431f-914b-650e32a2236c",
      "width": 1300,
      "x": -1300,
      "y": 700,
      "zOrder": 1000,
      "numberProperties": [],
      "stringProperties": [],
      "initialVariables": []
    },
    {
      "angle": 0,
      "customSize": true,
      "height": 700,
      "layer": "",
      "locked": true,
      "name": "blackscreen_1280_8",
      "persistentUuid": "c6b464a0-3f59-4018-9d41-1cc3f71dc53c",
      "width": 1300,
      "x": 0,
      "y": 700,
      "zOrder": 1000,
      "numberProperties": [],
      "stringProperties": [],
      "initialVariables": []
    },
    {
      "angle": 0,
      "customSize": true,
      "height": 700,
      "layer": "",
      "locked": true,
      "name": "blackscreen_1280_9",
      "persistentUuid": "045ca96c-9169-4afa-8244-162d4d7c7bb4",
      "width": 1300,
      "x": 1300,
      "y": 700,
      "zOrder": 1000,
      "numberProperties": [],
      "stringProperties": [],
      "initialVariables": []
    }
  ],
  "editionSettings": {
    "grid": false,
    "gridB": 255,
    "gridG": 180,
    "gridHeight": 50,
    "gridOffsetX": 0,
    "gridOffsetY": 0,
    "gridR": 158,
    "gridType": "rectangular",
    "gridWidth": 50,
    "snap": false,
    "windowMask": false,
    "zoomFactor": 0.106
  }
}