{
  "associatedLayout": "aventure_NEW",
  "lastChangeTimeStamp": 0,
  "name": "buildbox",
  "events": [
    {
      "disabled": false,
      "folded": false,
      "type": "BuiltinCommonInstructions::Standard",
      "conditions": [],
      "actions": [],
      "events": []
    },
    {
      "disabled": false,
      "folded": false,
      "type": "BuiltinCommonInstructions::Standard",
      "conditions": [],
      "actions": [],
      "events": []
    },
    {
      "disabled": false,
      "folded": false,
      "type": "BuiltinCommonInstructions::Standard",
      "conditions": [],
      "actions": [],
      "events": []
    },
    {
      "disabled": false,
      "folded": false,
      "type": "BuiltinCommonInstructions::Standard",
      "conditions": [
        {
          "type": {
            "inverted": false,
            "value": "Visible"
          },
          "parameters": [
            "build_inv_icon"
          ],
          "subInstructions": []
        },
        {
          "type": {
            "inverted": false,
            "value": "NbObjet"
          },
          "parameters": [
            "buildbox2",
            "=",
            "0"
          ],
          "subInstructions": []
        },
        {
          "type": {
            "inverted": false,
            "value": "SourisSurObjet"
          },
          "parameters": [
            "build_inv_icon",
            "",
            "no",
            ""
          ],
          "subInstructions": []
        },
        {
          "type": {
            "inverted": false,
            "value": "MouseButtonReleased"
          },
          "parameters": [
            "",
            "Left"
          ],
          "subInstructions": []
        },
        {
          "type": {
            "inverted": false,
            "value": "Timer"
          },
          "parameters": [
            "",
            "0.2",
            "\"buildselect\""
          ],
          "subInstructions": []
        },
        {
          "type": {
            "inverted": false,
            "value": "VarScene"
          },
          "parameters": [
            "buildselect",
            "=",
            "0"
          ],
          "subInstructions": []
        },
        {
          "type": {
            "inverted": false,
            "value": "BuiltinCommonInstructions::Once"
          },
          "parameters": [],
          "subInstructions": []
        }
      ],
      "actions": [
        {
          "type": {
            "inverted": false,
            "value": "Create"
          },
          "parameters": [
            "",
            "buildbox2",
            "cursor2.X()",
            "cursor2.Y()",
            "\"\""
          ],
          "subInstructions": []
        },
        {
          "type": {
            "inverted": false,
            "value": "Opacity"
          },
          "parameters": [
            "buildbox2",
            "=",
            "100"
          ],
          "subInstructions": []
        },
        {
          "type": {
            "inverted": false,
            "value": "ModVarScene"
          },
          "parameters": [
            "buildselect",
            "=",
            "1"
          ],
          "subInstructions": []
        },
        {
          "type": {
            "inverted": false,
            "value": "ResetTimer"
          },
          "parameters": [
            "",
            "\"buildselect\""
          ],
          "subInstructions": []
        },
        {
          "type": {
            "inverted": false,
            "value": "ModVarObjet"
          },
          "parameters": [
            "buildbox2",
            "selected",
            "=",
            "1"
          ],
          "subInstructions": []
        },
        {
          "type": {
            "inverted": false,
            "value": "ModVarScene"
          },
          "parameters": [
            "remaining",
            "=",
            "1"
          ],
          "subInstructions": []
        }
      ],
      "events": []
    },
    {
      "disabled": false,
      "folded": false,
      "type": "BuiltinCommonInstructions::Standard",
      "conditions": [],
      "actions": [],
      "events": []
    },
    {
      "disabled": false,
      "folded": false,
      "type": "BuiltinCommonInstructions::Standard",
      "conditions": [],
      "actions": [],
      "events": []
    },
    {
      "disabled": false,
      "folded": false,
      "type": "BuiltinCommonInstructions::Standard",
      "conditions": [
        {
          "type": {
            "inverted": true,
            "value": "CollisionNP"
          },
          "parameters": [
            "buildbox2",
            "BLOCKclick",
            "",
            "",
            "yes"
          ],
          "subInstructions": []
        },
        {
          "type": {
            "inverted": false,
            "value": "VarObjet"
          },
          "parameters": [
            "buildbox2",
            "selected",
            "=",
            "1"
          ],
          "subInstructions": []
        },
        {
          "type": {
            "inverted": false,
            "value": "VarScene"
          },
          "parameters": [
            "buildcraft",
            "=",
            "1"
          ],
          "subInstructions": []
        },
        {
          "type": {
            "inverted": false,
            "value": "VarScene"
          },
          "parameters": [
            "buildselect",
            "=",
            "1"
          ],
          "subInstructions": []
        },
        {
          "type": {
            "inverted": false,
            "value": "Timer"
          },
          "parameters": [
            "",
            "0.2",
            "\"buildselect\""
          ],
          "subInstructions": []
        },
        {
          "type": {
            "inverted": false,
            "value": "MouseButtonReleased"
          },
          "parameters": [
            "",
            "Left"
          ],
          "subInstructions": []
        },
        {
          "type": {
            "inverted": false,
            "value": "BuiltinCommonInstructions::Once"
          },
          "parameters": [],
          "subInstructions": []
        }
      ],
      "actions": [
        {
          "type": {
            "inverted": false,
            "value": "ChangeColor"
          },
          "parameters": [
            "buildbox2",
            "\"255;255;255\""
          ],
          "subInstructions": []
        },
        {
          "type": {
            "inverted": false,
            "value": "Opacity"
          },
          "parameters": [
            "buildbox2",
            "=",
            "255"
          ],
          "subInstructions": []
        },
        {
          "type": {
            "inverted": false,
            "value": "ModVarObjet"
          },
          "parameters": [
            "buildbox2",
            "selected",
            "=",
            "0"
          ],
          "subInstructions": []
        },
        {
          "type": {
            "inverted": false,
            "value": "ModVarScene"
          },
          "parameters": [
            "remaining",
            "=",
            "0"
          ],
          "subInstructions": []
        },
        {
          "type": {
            "inverted": false,
            "value": "ModVarGlobal"
          },
          "parameters": [
            "nestobjx",
            "=",
            "nestobj.X()"
          ],
          "subInstructions": []
        },
        {
          "type": {
            "inverted": false,
            "value": "ModVarGlobal"
          },
          "parameters": [
            "nestobjy",
            "=",
            "nestobj.Y()"
          ],
          "subInstructions": []
        },
        {
          "type": {
            "inverted": false,
            "value": "ModVarScene"
          },
          "parameters": [
            "buildcraft",
            "=",
            "0"
          ],
          "subInstructions": []
        },
        {
          "type": {
            "inverted": false,
            "value": "ModVarScene"
          },
          "parameters": [
            "buildselect",
            "=",
            "0"
          ],
          "subInstructions": []
        },
        {
          "type": {
            "inverted": false,
            "value": "ResetTimer"
          },
          "parameters": [
            "",
            "\"buildselect\""
          ],
          "subInstructions": []
        }
      ],
      "events": []
    },
    {
      "disabled": false,
      "folded": false,
      "type": "BuiltinCommonInstructions::Standard",
      "conditions": [],
      "actions": [],
      "events": []
    },
    {
      "disabled": false,
      "folded": false,
      "type": "BuiltinCommonInstructions::Standard",
      "conditions": [],
      "actions": [],
      "events": []
    },
    {
      "disabled": false,
      "folded": false,
      "type": "BuiltinCommonInstructions::Standard",
      "conditions": [],
      "actions": [],
      "events": []
    },
    {
      "disabled": false,
      "folded": false,
      "type": "BuiltinCommonInstructions::Standard",
      "conditions": [],
      "actions": [],
      "events": []
    },
    {
      "disabled": false,
      "folded": false,
      "type": "BuiltinCommonInstructions::Standard",
      "conditions": [
        {
          "type": {
            "inverted": false,
            "value": "NbObjet"
          },
          "parameters": [
            "build_fond",
            "<",
            "1"
          ],
          "subInstructions": []
        },
        {
          "type": {
            "inverted": false,
            "value": "CollisionNP"
          },
          "parameters": [
            "buildbox2",
            "hero",
            "20",
            "",
            ""
          ],
          "subInstructions": []
        },
        {
          "type": {
            "inverted": false,
            "value": "VarScene"
          },
          "parameters": [
            "buildselect",
            "=",
            "0"
          ],
          "subInstructions": []
        }
      ],
      "actions": [
        {
          "type": {
            "inverted": false,
            "value": "BuiltinExternalLayouts::CreateObjectsFromExternalLayout"
          },
          "parameters": [
            "",
            "\"buildthings\"",
            "0",
            "0"
          ],
          "subInstructions": []
        }
      ],
      "events": []
    },
    {
      "disabled": false,
      "folded": false,
      "type": "BuiltinCommonInstructions::Standard",
      "conditions": [],
      "actions": [],
      "events": []
    },
    {
      "disabled": false,
      "folded": false,
      "type": "BuiltinCommonInstructions::Standard",
      "conditions": [
        {
          "type": {
            "inverted": true,
            "value": "Distance"
          },
          "parameters": [
            "buildbox2",
            "hero",
            "150",
            ""
          ],
          "subInstructions": []
        }
      ],
      "actions": [
        {
          "type": {
            "inverted": false,
            "value": "Delete"
          },
          "parameters": [
            "buildthings_group",
            "build_fond"
          ],
          "subInstructions": []
        }
      ],
      "events": []
    },
    {
      "disabled": false,
      "folded": false,
      "type": "BuiltinCommonInstructions::Standard",
      "conditions": [],
      "actions": [],
      "events": []
    },
    {
      "disabled": false,
      "folded": false,
      "type": "BuiltinCommonInstructions::Standard",
      "conditions": [],
      "actions": [],
      "events": []
    },
    {
      "disabled": false,
      "folded": false,
      "type": "BuiltinCommonInstructions::Standard",
      "conditions": [],
      "actions": [],
      "events": []
    },
    {
      "disabled": false,
      "folded": false,
      "type": "BuiltinCommonInstructions::Standard",
      "conditions": [],
      "actions": [],
      "events": []
    },
    {
      "disabled": false,
      "folded": false,
      "type": "BuiltinCommonInstructions::Standard",
      "conditions": [],
      "actions": [],
      "events": []
    },
    {
      "disabled": false,
      "folded": false,
      "type": "BuiltinCommonInstructions::Standard",
      "conditions": [],
      "actions": [],
      "events": []
    },
    {
      "disabled": false,
      "folded": false,
      "type": "BuiltinCommonInstructions::Standard",
      "conditions": [
        {
          "type": {
            "inverted": false,
            "value": "Visible"
          },
          "parameters": [
            "build_floor01"
          ],
          "subInstructions": []
        },
        {
          "type": {
            "inverted": false,
            "value": "VarScene"
          },
          "parameters": [
            "buildselect",
            "=",
            "0"
          ],
          "subInstructions": []
        },
        {
          "type": {
            "inverted": false,
            "value": "SourisSurObjet"
          },
          "parameters": [
            "build_floor01",
            "",
            "no",
            ""
          ],
          "subInstructions": []
        },
        {
          "type": {
            "inverted": false,
            "value": "MouseButtonPressed"
          },
          "parameters": [
            "",
            "Left"
          ],
          "subInstructions": []
        }
      ],
      "actions": [
        {
          "type": {
            "inverted": false,
            "value": "Create"
          },
          "parameters": [
            "",
            "herbe01",
            "cursor2.X()",
            "cursor2.Y()",
            "\"\""
          ],
          "subInstructions": []
        },
        {
          "type": {
            "inverted": false,
            "value": "ModVarObjet"
          },
          "parameters": [
            "herbe01",
            "selected",
            "=",
            "1"
          ],
          "subInstructions": []
        },
        {
          "type": {
            "inverted": false,
            "value": "Opacity"
          },
          "parameters": [
            "herbe01",
            "=",
            "150"
          ],
          "subInstructions": []
        },
        {
          "type": {
            "inverted": false,
            "value": "ModVarScene"
          },
          "parameters": [
            "buildselect",
            "=",
            "1"
          ],
          "subInstructions": []
        },
        {
          "type": {
            "inverted": false,
            "value": "ResetTimer"
          },
          "parameters": [
            "",
            "\"buildselect\""
          ],
          "subInstructions": []
        }
      ],
      "events": []
    },
    {
      "disabled": true,
      "folded": false,
      "type": "BuiltinCommonInstructions::Standard",
      "conditions": [
        {
          "type": {
            "inverted": false,
            "value": "Timer"
          },
          "parameters": [
            "",
            "0.1",
            "\"buildselect\""
          ],
          "subInstructions": []
        },
        {
          "type": {
            "inverted": false,
            "value": "BuiltinCommonInstructions::Once"
          },
          "parameters": [],
          "subInstructions": []
        }
      ],
      "actions": [],
      "events": []
    },
    {
      "disabled": false,
      "folded": false,
      "type": "BuiltinCommonInstructions::Standard",
      "conditions": [
        {
          "type": {
            "inverted": true,
            "value": "CollisionNP"
          },
          "parameters": [
            "herbe01",
            "BLOCKclick",
            "",
            "",
            "yes"
          ],
          "subInstructions": []
        },
        {
          "type": {
            "inverted": false,
            "value": "VarObjet"
          },
          "parameters": [
            "herbe01",
            "selected",
            "=",
            "1"
          ],
          "subInstructions": []
        },
        {
          "type": {
            "inverted": false,
            "value": "VarScene"
          },
          "parameters": [
            "buildselect",
            "=",
            "1"
          ],
          "subInstructions": []
        },
        {
          "type": {
            "inverted": false,
            "value": "Timer"
          },
          "parameters": [
            "",
            "0.1",
            "\"buildselect\""
          ],
          "subInstructions": []
        },
        {
          "type": {
            "inverted": false,
            "value": "MouseButtonReleased"
          },
          "parameters": [
            "",
            "Left"
          ],
          "subInstructions": []
        }
      ],
      "actions": [
        {
          "type": {
            "inverted": false,
            "value": "ChangeColor"
          },
          "parameters": [
            "herbe01",
            "\"255;255;255\""
          ],
          "subInstructions": []
        },
        {
          "type": {
            "inverted": false,
            "value": "Opacity"
          },
          "parameters": [
            "herbe01",
            "=",
            "255"
          ],
          "subInstructions": []
        },
        {
          "type": {
            "inverted": false,
            "value": "ModVarObjet"
          },
          "parameters": [
            "herbe01",
            "selected",
            "=",
            "0"
          ],
          "subInstructions": []
        },
        {
          "type": {
            "inverted": false,
            "value": "ModVarScene"
          },
          "parameters": [
            "buildselect",
            "=",
            "0"
          ],
          "subInstructions": []
        },
        {
          "type": {
            "inverted": false,
            "value": "PlatformBehavior::ChangePlatformType"
          },
          "parameters": [
            "herbe01",
            "Platform",
            "\"Platform\""
          ],
          "subInstructions": []
        }
      ],
      "events": [
        {
          "disabled": true,
          "folded": false,
          "type": "BuiltinCommonInstructions::Standard",
          "conditions": [
            {
              "type": {
                "inverted": false,
                "value": "BuiltinCommonInstructions::Once"
              },
              "parameters": [],
              "subInstructions": []
            }
          ],
          "actions": [
            {
              "type": {
                "inverted": false,
                "value": "Create"
              },
              "parameters": [
                "",
                "herbe01",
                "cursor2.X()",
                "cursor2.Y()",
                "\"\""
              ],
              "subInstructions": []
            },
            {
              "type": {
                "inverted": false,
                "value": "ModVarObjet"
              },
              "parameters": [
                "herbe01",
                "selected",
                "=",
                "1"
              ],
              "subInstructions": []
            },
            {
              "type": {
                "inverted": false,
                "value": "Opacity"
              },
              "parameters": [
                "herbe01",
                "=",
                "150"
              ],
              "subInstructions": []
            },
            {
              "type": {
                "inverted": false,
                "value": "ModVarScene"
              },
              "parameters": [
                "buildselect",
                "=",
                "1"
              ],
              "subInstructions": []
            },
            {
              "type": {
                "inverted": false,
                "value": "ResetTimer"
              },
              "parameters": [
                "",
                "\"buildselect\""
              ],
              "subInstructions": []
            }
          ],
          "events": []
        }
      ]
    },
    {
      "disabled": true,
      "folded": false,
      "type": "BuiltinCommonInstructions::Standard",
      "conditions": [],
      "actions": [
        {
          "type": {
            "inverted": false,
            "value": "ResetTimer"
          },
          "parameters": [
            "",
            "\"buildselect\""
          ],
          "subInstructions": []
        }
      ],
      "events": []
    },
    {
      "disabled": false,
      "folded": false,
      "type": "BuiltinCommonInstructions::ForEach",
      "object": "herbe01",
      "conditions": [
        {
          "type": {
            "inverted": false,
            "value": "VarObjet"
          },
          "parameters": [
            "herbe01",
            "selected",
            "=",
            "1"
          ],
          "subInstructions": []
        }
      ],
      "actions": [
        {
          "type": {
            "inverted": false,
            "value": "MettreXY"
          },
          "parameters": [
            "herbe01",
            "=",
            "cursor2.X()",
            "=",
            "cursor2.Y()"
          ],
          "subInstructions": []
        },
        {
          "type": {
            "inverted": false,
            "value": "PlatformBehavior::ChangePlatformType"
          },
          "parameters": [
            "herbe01",
            "Platform",
            "\"Ladder\""
          ],
          "subInstructions": []
        }
      ],
      "events": []
    },
    {
      "disabled": false,
      "folded": false,
      "type": "BuiltinCommonInstructions::ForEach",
      "object": "herbe01",
      "conditions": [
        {
          "type": {
            "inverted": false,
            "value": "VarObjet"
          },
          "parameters": [
            "herbe01",
            "selected",
            "=",
            "1"
          ],
          "subInstructions": []
        },
        {
          "type": {
            "inverted": false,
            "value": "NbObjet"
          },
          "parameters": [
            "build_fond",
            "<",
            "1"
          ],
          "subInstructions": []
        }
      ],
      "actions": [
        {
          "type": {
            "inverted": false,
            "value": "Delete"
          },
          "parameters": [
            "herbe01",
            "build_fond"
          ],
          "subInstructions": []
        },
        {
          "type": {
            "inverted": false,
            "value": "ModVarScene"
          },
          "parameters": [
            "buildselect",
            "=",
            "0"
          ],
          "subInstructions": []
        }
      ],
      "events": []
    },
    {
      "disabled": false,
      "folded": false,
      "type": "BuiltinCommonInstructions::Standard",
      "conditions": [],
      "actions": [],
      "events": []
    },
    {
      "disabled": false,
      "folded": false,
      "type": "BuiltinCommonInstructions::Standard",
      "conditions": [],
      "actions": [],
      "events": []
    },
    {
      "disabled": false,
      "folded": false,
      "type": "BuiltinCommonInstructions::Standard",
      "conditions": [],
      "actions": [],
      "events": []
    },
    {
      "disabled": true,
      "folded": false,
      "type": "BuiltinCommonInstructions::Standard",
      "conditions": [
        {
          "type": {
            "inverted": false,
            "value": "Visible"
          },
          "parameters": [
            "build_floor01"
          ],
          "subInstructions": []
        },
        {
          "type": {
            "inverted": false,
            "value": "VarScene"
          },
          "parameters": [
            "buildselect",
            "=",
            "0"
          ],
          "subInstructions": []
        },
        {
          "type": {
            "inverted": false,
            "value": "SourisSurObjet"
          },
          "parameters": [
            "build_floor01",
            "",
            "no",
            ""
          ],
          "subInstructions": []
        },
        {
          "type": {
            "inverted": false,
            "value": "MouseButtonReleased"
          },
          "parameters": [
            "",
            "Left"
          ],
          "subInstructions": []
        },
        {
          "type": {
            "inverted": false,
            "value": "Timer"
          },
          "parameters": [
            "",
            "0.2",
            "\"buildselect\""
          ],
          "subInstructions": []
        },
        {
          "type": {
            "inverted": false,
            "value": "BuiltinCommonInstructions::Once"
          },
          "parameters": [],
          "subInstructions": []
        }
      ],
      "actions": [
        {
          "type": {
            "inverted": false,
            "value": "Create"
          },
          "parameters": [
            "",
            "herbe01",
            "cursor2.X()",
            "cursor2.Y()",
            "\"\""
          ],
          "subInstructions": []
        },
        {
          "type": {
            "inverted": false,
            "value": "ModVarObjet"
          },
          "parameters": [
            "herbe01",
            "selected",
            "=",
            "1"
          ],
          "subInstructions": []
        },
        {
          "type": {
            "inverted": false,
            "value": "Opacity"
          },
          "parameters": [
            "herbe01",
            "=",
            "150"
          ],
          "subInstructions": []
        },
        {
          "type": {
            "inverted": false,
            "value": "ModVarScene"
          },
          "parameters": [
            "buildselect",
            "=",
            "1"
          ],
          "subInstructions": []
        },
        {
          "type": {
            "inverted": false,
            "value": "ResetTimer"
          },
          "parameters": [
            "",
            "\"buildselect\""
          ],
          "subInstructions": []
        }
      ],
      "events": []
    },
    {
      "disabled": false,
      "folded": false,
      "type": "BuiltinCommonInstructions::Standard",
      "conditions": [],
      "actions": [],
      "events": []
    },
    {
      "disabled": false,
      "folded": false,
      "type": "BuiltinCommonInstructions::Standard",
      "conditions": [],
      "actions": [],
      "events": []
    },
    {
      "disabled": false,
      "folded": false,
      "type": "BuiltinCommonInstructions::Standard",
      "conditions": [],
      "actions": [],
      "events": []
    },
    {
      "disabled": true,
      "folded": false,
      "type": "BuiltinCommonInstructions::ForEach",
      "object": "build_objects",
      "conditions": [
        {
          "type": {
            "inverted": false,
            "value": "VarObjet"
          },
          "parameters": [
            "build_objects",
            "selected",
            "=",
            "1"
          ],
          "subInstructions": []
        }
      ],
      "actions": [
        {
          "type": {
            "inverted": false,
            "value": "Create"
          },
          "parameters": [
            "",
            "herbe01",
            "cursor2.X()",
            "cursor2.Y()",
            "\"\""
          ],
          "subInstructions": []
        }
      ],
      "events": []
    },
    {
      "disabled": false,
      "folded": false,
      "type": "BuiltinCommonInstructions::Standard",
      "conditions": [],
      "actions": [],
      "events": []
    },
    {
      "disabled": false,
      "folded": false,
      "type": "BuiltinCommonInstructions::Standard",
      "conditions": [],
      "actions": [],
      "events": []
    },
    {
      "disabled": false,
      "folded": false,
      "type": "BuiltinCommonInstructions::Standard",
      "conditions": [],
      "actions": [],
      "events": []
    },
    {
      "disabled": false,
      "folded": false,
      "type": "BuiltinCommonInstructions::Standard",
      "conditions": [],
      "actions": [],
      "events": []
    },
    {
      "disabled": false,
      "folded": false,
      "type": "BuiltinCommonInstructions::Standard",
      "conditions": [],
      "actions": [],
      "events": []
    },
    {
      "disabled": false,
      "folded": false,
      "type": "BuiltinCommonInstructions::Standard",
      "conditions": [],
      "actions": [],
      "events": []
    },
    {
      "disabled": false,
      "folded": false,
      "type": "BuiltinCommonInstructions::Standard",
      "conditions": [],
      "actions": [],
      "events": []
    },
    {
      "disabled": false,
      "folded": false,
      "type": "BuiltinCommonInstructions::Standard",
      "conditions": [
        {
          "type": {
            "inverted": false,
            "value": "Visible"
          },
          "parameters": [
            "build_floor02"
          ],
          "subInstructions": []
        },
        {
          "type": {
            "inverted": false,
            "value": "VarScene"
          },
          "parameters": [
            "buildselect",
            "=",
            "0"
          ],
          "subInstructions": []
        },
        {
          "type": {
            "inverted": false,
            "value": "SourisSurObjet"
          },
          "parameters": [
            "build_floor02",
            "",
            "no",
            ""
          ],
          "subInstructions": []
        },
        {
          "type": {
            "inverted": false,
            "value": "MouseButtonReleased"
          },
          "parameters": [
            "",
            "Left"
          ],
          "subInstructions": []
        },
        {
          "type": {
            "inverted": false,
            "value": "Timer"
          },
          "parameters": [
            "",
            "0.2",
            "\"buildselect\""
          ],
          "subInstructions": []
        },
        {
          "type": {
            "inverted": false,
            "value": "BuiltinCommonInstructions::Once"
          },
          "parameters": [],
          "subInstructions": []
        }
      ],
      "actions": [
        {
          "type": {
            "inverted": false,
            "value": "Create"
          },
          "parameters": [
            "",
            "herbe02",
            "cursor2.X()",
            "cursor2.Y()",
            "\"\""
          ],
          "subInstructions": []
        },
        {
          "type": {
            "inverted": false,
            "value": "ModVarObjet"
          },
          "parameters": [
            "herbe02",
            "selected",
            "=",
            "1"
          ],
          "subInstructions": []
        },
        {
          "type": {
            "inverted": false,
            "value": "Opacity"
          },
          "parameters": [
            "herbe02",
            "=",
            "150"
          ],
          "subInstructions": []
        },
        {
          "type": {
            "inverted": false,
            "value": "ModVarScene"
          },
          "parameters": [
            "buildselect",
            "=",
            "1"
          ],
          "subInstructions": []
        },
        {
          "type": {
            "inverted": false,
            "value": "ResetTimer"
          },
          "parameters": [
            "",
            "\"buildselect\""
          ],
          "subInstructions": []
        }
      ],
      "events": []
    },
    {
      "disabled": false,
      "folded": false,
      "type": "BuiltinCommonInstructions::Standard",
      "conditions": [],
      "actions": [],
      "events": []
    },
    {
      "disabled": false,
      "folded": false,
      "type": "BuiltinCommonInstructions::Standard",
      "conditions": [
        {
          "type": {
            "inverted": true,
            "value": "CollisionNP"
          },
          "parameters": [
            "herbe02",
            "BLOCKclick",
            "",
            "",
            "yes"
          ],
          "subInstructions": []
        },
        {
          "type": {
            "inverted": false,
            "value": "VarObjet"
          },
          "parameters": [
            "herbe02",
            "selected",
            "=",
            "1"
          ],
          "subInstructions": []
        },
        {
          "type": {
            "inverted": false,
            "value": "VarScene"
          },
          "parameters": [
            "buildselect",
            "=",
            "1"
          ],
          "subInstructions": []
        },
        {
          "type": {
            "inverted": false,
            "value": "Timer"
          },
          "parameters": [
            "",
            "0.2",
            "\"buildselect\""
          ],
          "subInstructions": []
        },
        {
          "type": {
            "inverted": false,
            "value": "MouseButtonReleased"
          },
          "parameters": [
            "",
            "Left"
          ],
          "subInstructions": []
        },
        {
          "type": {
            "inverted": false,
            "value": "BuiltinCommonInstructions::Once"
          },
          "parameters": [],
          "subInstructions": []
        }
      ],
      "actions": [
        {
          "type": {
            "inverted": false,
            "value": "ChangeColor"
          },
          "parameters": [
            "herbe02",
            "\"255;255;255\""
          ],
          "subInstructions": []
        },
        {
          "type": {
            "inverted": false,
            "value": "Opacity"
          },
          "parameters": [
            "herbe02",
            "=",
            "255"
          ],
          "subInstructions": []
        },
        {
          "type": {
            "inverted": false,
            "value": "ModVarObjet"
          },
          "parameters": [
            "herbe02",
            "selected",
            "=",
            "0"
          ],
          "subInstructions": []
        },
        {
          "type": {
            "inverted": false,
            "value": "ModVarScene"
          },
          "parameters": [
            "buildselect",
            "=",
            "0"
          ],
          "subInstructions": []
        },
        {
          "type": {
            "inverted": false,
            "value": "ResetTimer"
          },
          "parameters": [
            "",
            "\"buildselect\""
          ],
          "subInstructions": []
        },
        {
          "type": {
            "inverted": false,
            "value": "PlatformBehavior::ChangePlatformType"
          },
          "parameters": [
            "herbe02",
            "Platform",
            "\"Platform\""
          ],
          "subInstructions": []
        }
      ],
      "events": []
    },
    {
      "disabled": false,
      "folded": false,
      "type": "BuiltinCommonInstructions::Standard",
      "conditions": [],
      "actions": [],
      "events": []
    },
    {
      "disabled": false,
      "folded": false,
      "type": "BuiltinCommonInstructions::ForEach",
      "object": "herbe02",
      "conditions": [
        {
          "type": {
            "inverted": false,
            "value": "VarObjet"
          },
          "parameters": [
            "herbe02",
            "selected",
            "=",
            "1"
          ],
          "subInstructions": []
        }
      ],
      "actions": [
        {
          "type": {
            "inverted": false,
            "value": "MettreXY"
          },
          "parameters": [
            "herbe02",
            "=",
            "cursor2.X()",
            "=",
            "cursor2.Y()"
          ],
          "subInstructions": []
        },
        {
          "type": {
            "inverted": false,
            "value": "PlatformBehavior::ChangePlatformType"
          },
          "parameters": [
            "herbe02",
            "Platform",
            "\"Ladder\""
          ],
          "subInstructions": []
        }
      ],
      "events": []
    },
    {
      "disabled": false,
      "folded": false,
      "type": "BuiltinCommonInstructions::ForEach",
      "object": "herbe02",
      "conditions": [
        {
          "type": {
            "inverted": false,
            "value": "VarObjet"
          },
          "parameters": [
            "herbe02",
            "selected",
            "=",
            "1"
          ],
          "subInstructions": []
        },
        {
          "type": {
            "inverted": false,
            "value": "NbObjet"
          },
          "parameters": [
            "build_fond",
            "<",
            "1"
          ],
          "subInstructions": []
        }
      ],
      "actions": [
        {
          "type": {
            "inverted": false,
            "value": "Delete"
          },
          "parameters": [
            "herbe02",
            "build_fond"
          ],
          "subInstructions": []
        },
        {
          "type": {
            "inverted": false,
            "value": "ModVarScene"
          },
          "parameters": [
            "buildselect",
            "=",
            "0"
          ],
          "subInstructions": []
        }
      ],
      "events": []
    },
    {
      "disabled": false,
      "folded": false,
      "type": "BuiltinCommonInstructions::Standard",
      "conditions": [],
      "actions": [],
      "events": []
    },
    {
      "disabled": false,
      "folded": false,
      "type": "BuiltinCommonInstructions::Standard",
      "conditions": [],
      "actions": [],
      "events": []
    },
    {
      "disabled": false,
      "folded": false,
      "type": "BuiltinCommonInstructions::Standard",
      "conditions": [],
      "actions": [],
      "events": []
    },
    {
      "disabled": false,
      "folded": false,
      "type": "BuiltinCommonInstructions::Standard",
      "conditions": [
        {
          "type": {
            "inverted": false,
            "value": "Visible"
          },
          "parameters": [
            "build_neige"
          ],
          "subInstructions": []
        },
        {
          "type": {
            "inverted": false,
            "value": "VarScene"
          },
          "parameters": [
            "buildselect",
            "=",
            "0"
          ],
          "subInstructions": []
        },
        {
          "type": {
            "inverted": false,
            "value": "SourisSurObjet"
          },
          "parameters": [
            "build_neige",
            "",
            "no",
            ""
          ],
          "subInstructions": []
        },
        {
          "type": {
            "inverted": false,
            "value": "MouseButtonReleased"
          },
          "parameters": [
            "",
            "Left"
          ],
          "subInstructions": []
        },
        {
          "type": {
            "inverted": false,
            "value": "Timer"
          },
          "parameters": [
            "",
            "0.2",
            "\"buildselect\""
          ],
          "subInstructions": []
        },
        {
          "type": {
            "inverted": false,
            "value": "BuiltinCommonInstructions::Once"
          },
          "parameters": [],
          "subInstructions": []
        }
      ],
      "actions": [
        {
          "type": {
            "inverted": false,
            "value": "Create"
          },
          "parameters": [
            "",
            "neige01",
            "cursor2.X()+25",
            "cursor2.Y()+25",
            "\"\""
          ],
          "subInstructions": []
        },
        {
          "type": {
            "inverted": false,
            "value": "ModVarObjet"
          },
          "parameters": [
            "neige01",
            "selected",
            "=",
            "1"
          ],
          "subInstructions": []
        },
        {
          "type": {
            "inverted": false,
            "value": "Opacity"
          },
          "parameters": [
            "neige01",
            "=",
            "150"
          ],
          "subInstructions": []
        },
        {
          "type": {
            "inverted": false,
            "value": "ModVarScene"
          },
          "parameters": [
            "buildselect",
            "=",
            "1"
          ],
          "subInstructions": []
        },
        {
          "type": {
            "inverted": false,
            "value": "ResetTimer"
          },
          "parameters": [
            "",
            "\"buildselect\""
          ],
          "subInstructions": []
        }
      ],
      "events": []
    },
    {
      "disabled": false,
      "folded": false,
      "type": "BuiltinCommonInstructions::Standard",
      "conditions": [],
      "actions": [],
      "events": []
    },
    {
      "disabled": false,
      "folded": false,
      "type": "BuiltinCommonInstructions::Standard",
      "conditions": [
        {
          "type": {
            "inverted": true,
            "value": "CollisionNP"
          },
          "parameters": [
            "neige01",
            "BLOCKclick",
            "",
            "",
            "yes"
          ],
          "subInstructions": []
        },
        {
          "type": {
            "inverted": false,
            "value": "VarObjet"
          },
          "parameters": [
            "neige01",
            "selected",
            "=",
            "1"
          ],
          "subInstructions": []
        },
        {
          "type": {
            "inverted": false,
            "value": "VarScene"
          },
          "parameters": [
            "buildselect",
            "=",
            "1"
          ],
          "subInstructions": []
        },
        {
          "type": {
            "inverted": false,
            "value": "Timer"
          },
          "parameters": [
            "",
            "0.2",
            "\"buildselect\""
          ],
          "subInstructions": []
        },
        {
          "type": {
            "inverted": false,
            "value": "MouseButtonReleased"
          },
          "parameters": [
            "",
            "Left"
          ],
          "subInstructions": []
        },
        {
          "type": {
            "inverted": false,
            "value": "BuiltinCommonInstructions::Once"
          },
          "parameters": [],
          "subInstructions": []
        }
      ],
      "actions": [
        {
          "type": {
            "inverted": false,
            "value": "ChangeColor"
          },
          "parameters": [
            "neige01",
            "\"255;255;255\""
          ],
          "subInstructions": []
        },
        {
          "type": {
            "inverted": false,
            "value": "Opacity"
          },
          "parameters": [
            "neige01",
            "=",
            "255"
          ],
          "subInstructions": []
        },
        {
          "type": {
            "inverted": false,
            "value": "ModVarObjet"
          },
          "parameters": [
            "neige01",
            "selected",
            "=",
            "0"
          ],
          "subInstructions": []
        },
        {
          "type": {
            "inverted": false,
            "value": "ModVarScene"
          },
          "parameters": [
            "buildselect",
            "=",
            "0"
          ],
          "subInstructions": []
        },
        {
          "type": {
            "inverted": false,
            "value": "ResetTimer"
          },
          "parameters": [
            "",
            "\"buildselect\""
          ],
          "subInstructions": []
        },
        {
          "type": {
            "inverted": false,
            "value": "PlatformBehavior::ChangePlatformType"
          },
          "parameters": [
            "neige01",
            "Platform",
            "\"Platform\""
          ],
          "subInstructions": []
        }
      ],
      "events": []
    },
    {
      "disabled": false,
      "folded": false,
      "type": "BuiltinCommonInstructions::Standard",
      "conditions": [],
      "actions": [],
      "events": []
    },
    {
      "disabled": false,
      "folded": false,
      "type": "BuiltinCommonInstructions::Standard",
      "conditions": [],
      "actions": [],
      "events": []
    },
    {
      "disabled": false,
      "folded": false,
      "type": "BuiltinCommonInstructions::ForEach",
      "object": "neige01",
      "conditions": [
        {
          "type": {
            "inverted": false,
            "value": "VarObjet"
          },
          "parameters": [
            "neige01",
            "selected",
            "=",
            "1"
          ],
          "subInstructions": []
        }
      ],
      "actions": [
        {
          "type": {
            "inverted": false,
            "value": "MettreXY"
          },
          "parameters": [
            "neige01",
            "=",
            "cursor2.X()+25",
            "=",
            "cursor2.Y()+25"
          ],
          "subInstructions": []
        },
        {
          "type": {
            "inverted": false,
            "value": "PlatformBehavior::ChangePlatformType"
          },
          "parameters": [
            "neige01",
            "Platform",
            "\"Ladder\""
          ],
          "subInstructions": []
        }
      ],
      "events": []
    },
    {
      "disabled": false,
      "folded": false,
      "type": "BuiltinCommonInstructions::Standard",
      "conditions": [],
      "actions": [],
      "events": []
    },
    {
      "disabled": false,
      "folded": false,
      "type": "BuiltinCommonInstructions::ForEach",
      "object": "neige01",
      "conditions": [
        {
          "type": {
            "inverted": false,
            "value": "VarObjet"
          },
          "parameters": [
            "neige01",
            "selected",
            "=",
            "1"
          ],
          "subInstructions": []
        },
        {
          "type": {
            "inverted": false,
            "value": "NbObjet"
          },
          "parameters": [
            "build_fond",
            "<",
            "1"
          ],
          "subInstructions": []
        }
      ],
      "actions": [
        {
          "type": {
            "inverted": false,
            "value": "Delete"
          },
          "parameters": [
            "neige01",
            "build_fond"
          ],
          "subInstructions": []
        },
        {
          "type": {
            "inverted": false,
            "value": "ModVarScene"
          },
          "parameters": [
            "buildselect",
            "=",
            "0"
          ],
          "subInstructions": []
        }
      ],
      "events": []
    },
    {
      "disabled": false,
      "folded": false,
      "type": "BuiltinCommonInstructions::Standard",
      "conditions": [],
      "actions": [],
      "events": []
    },
    {
      "disabled": false,
      "folded": false,
      "type": "BuiltinCommonInstructions::Standard",
      "conditions": [],
      "actions": [],
      "events": []
    },
    {
      "disabled": false,
      "folded": false,
      "type": "BuiltinCommonInstructions::Standard",
      "conditions": [
        {
          "type": {
            "inverted": false,
            "value": "Visible"
          },
          "parameters": [
            "build_sable"
          ],
          "subInstructions": []
        },
        {
          "type": {
            "inverted": false,
            "value": "VarScene"
          },
          "parameters": [
            "buildselect",
            "=",
            "0"
          ],
          "subInstructions": []
        },
        {
          "type": {
            "inverted": false,
            "value": "SourisSurObjet"
          },
          "parameters": [
            "build_sable",
            "",
            "no",
            ""
          ],
          "subInstructions": []
        },
        {
          "type": {
            "inverted": false,
            "value": "MouseButtonReleased"
          },
          "parameters": [
            "",
            "Left"
          ],
          "subInstructions": []
        },
        {
          "type": {
            "inverted": false,
            "value": "Timer"
          },
          "parameters": [
            "",
            "0.2",
            "\"buildselect\""
          ],
          "subInstructions": []
        },
        {
          "type": {
            "inverted": false,
            "value": "BuiltinCommonInstructions::Once"
          },
          "parameters": [],
          "subInstructions": []
        }
      ],
      "actions": [
        {
          "type": {
            "inverted": false,
            "value": "Create"
          },
          "parameters": [
            "",
            "sable01",
            "cursor2.X()",
            "cursor2.Y()",
            "\"\""
          ],
          "subInstructions": []
        },
        {
          "type": {
            "inverted": false,
            "value": "ModVarObjet"
          },
          "parameters": [
            "sable01",
            "selected",
            "=",
            "1"
          ],
          "subInstructions": []
        },
        {
          "type": {
            "inverted": false,
            "value": "Opacity"
          },
          "parameters": [
            "sable01",
            "=",
            "150"
          ],
          "subInstructions": []
        },
        {
          "type": {
            "inverted": false,
            "value": "ModVarScene"
          },
          "parameters": [
            "buildselect",
            "=",
            "1"
          ],
          "subInstructions": []
        },
        {
          "type": {
            "inverted": false,
            "value": "ResetTimer"
          },
          "parameters": [
            "",
            "\"buildselect\""
          ],
          "subInstructions": []
        }
      ],
      "events": []
    },
    {
      "disabled": false,
      "folded": false,
      "type": "BuiltinCommonInstructions::Standard",
      "conditions": [
        {
          "type": {
            "inverted": true,
            "value": "CollisionNP"
          },
          "parameters": [
            "sable01",
            "BLOCKclick",
            "",
            "",
            "yes"
          ],
          "subInstructions": []
        },
        {
          "type": {
            "inverted": false,
            "value": "VarObjet"
          },
          "parameters": [
            "sable01",
            "selected",
            "=",
            "1"
          ],
          "subInstructions": []
        },
        {
          "type": {
            "inverted": false,
            "value": "VarScene"
          },
          "parameters": [
            "buildselect",
            "=",
            "1"
          ],
          "subInstructions": []
        },
        {
          "type": {
            "inverted": false,
            "value": "Timer"
          },
          "parameters": [
            "",
            "0.2",
            "\"buildselect\""
          ],
          "subInstructions": []
        },
        {
          "type": {
            "inverted": false,
            "value": "MouseButtonReleased"
          },
          "parameters": [
            "",
            "Left"
          ],
          "subInstructions": []
        },
        {
          "type": {
            "inverted": false,
            "value": "BuiltinCommonInstructions::Once"
          },
          "parameters": [],
          "subInstructions": []
        }
      ],
      "actions": [
        {
          "type": {
            "inverted": false,
            "value": "ChangeColor"
          },
          "parameters": [
            "sable01",
            "\"255;255;255\""
          ],
          "subInstructions": []
        },
        {
          "type": {
            "inverted": false,
            "value": "Opacity"
          },
          "parameters": [
            "sable01",
            "=",
            "255"
          ],
          "subInstructions": []
        },
        {
          "type": {
            "inverted": false,
            "value": "ModVarObjet"
          },
          "parameters": [
            "sable01",
            "selected",
            "=",
            "0"
          ],
          "subInstructions": []
        },
        {
          "type": {
            "inverted": false,
            "value": "ModVarScene"
          },
          "parameters": [
            "buildselect",
            "=",
            "0"
          ],
          "subInstructions": []
        },
        {
          "type": {
            "inverted": false,
            "value": "ResetTimer"
          },
          "parameters": [
            "",
            "\"buildselect\""
          ],
          "subInstructions": []
        },
        {
          "type": {
            "inverted": false,
            "value": "PlatformBehavior::ChangePlatformType"
          },
          "parameters": [
            "sable01",
            "Platform",
            "\"Platform\""
          ],
          "subInstructions": []
        }
      ],
      "events": []
    },
    {
      "disabled": false,
      "folded": false,
      "type": "BuiltinCommonInstructions::Standard",
      "conditions": [],
      "actions": [],
      "events": []
    },
    {
      "disabled": false,
      "folded": false,
      "type": "BuiltinCommonInstructions::ForEach",
      "object": "sable01",
      "conditions": [
        {
          "type": {
            "inverted": false,
            "value": "VarObjet"
          },
          "parameters": [
            "sable01",
            "selected",
            "=",
            "1"
          ],
          "subInstructions": []
        }
      ],
      "actions": [
        {
          "type": {
            "inverted": false,
            "value": "MettreXY"
          },
          "parameters": [
            "sable01",
            "=",
            "cursor2.X()",
            "=",
            "cursor2.Y()"
          ],
          "subInstructions": []
        },
        {
          "type": {
            "inverted": false,
            "value": "PlatformBehavior::ChangePlatformType"
          },
          "parameters": [
            "sable01",
            "Platform",
            "\"Ladder\""
          ],
          "subInstructions": []
        }
      ],
      "events": []
    },
    {
      "disabled": false,
      "folded": false,
      "type": "BuiltinCommonInstructions::ForEach",
      "object": "sable01",
      "conditions": [
        {
          "type": {
            "inverted": false,
            "value": "VarObjet"
          },
          "parameters": [
            "sable01",
            "selected",
            "=",
            "1"
          ],
          "subInstructions": []
        },
        {
          "type": {
            "inverted": false,
            "value": "NbObjet"
          },
          "parameters": [
            "build_fond",
            "<",
            "1"
          ],
          "subInstructions": []
        }
      ],
      "actions": [
        {
          "type": {
            "inverted": false,
            "value": "Delete"
          },
          "parameters": [
            "sable01",
            "build_fond"
          ],
          "subInstructions": []
        },
        {
          "type": {
            "inverted": false,
            "value": "ModVarScene"
          },
          "parameters": [
            "buildselect",
            "=",
            "0"
          ],
          "subInstructions": []
        }
      ],
      "events": []
    },
    {
      "disabled": false,
      "folded": false,
      "type": "BuiltinCommonInstructions::Standard",
      "conditions": [],
      "actions": [],
      "events": []
    },
    {
      "disabled": false,
      "folded": false,
      "type": "BuiltinCommonInstructions::Standard",
      "conditions": [],
      "actions": [],
      "events": []
    },
    {
      "disabled": false,
      "folded": false,
      "type": "BuiltinCommonInstructions::Standard",
      "conditions": [],
      "actions": [],
      "events": []
    },
    {
      "disabled": false,
      "folded": false,
      "type": "BuiltinCommonInstructions::Standard",
      "conditions": [
        {
          "type": {
            "inverted": false,
            "value": "Visible"
          },
          "parameters": [
            "build_feu"
          ],
          "subInstructions": []
        },
        {
          "type": {
            "inverted": false,
            "value": "VarScene"
          },
          "parameters": [
            "buildselect",
            "=",
            "0"
          ],
          "subInstructions": []
        },
        {
          "type": {
            "inverted": false,
            "value": "SourisSurObjet"
          },
          "parameters": [
            "build_feu",
            "",
            "no",
            ""
          ],
          "subInstructions": []
        },
        {
          "type": {
            "inverted": false,
            "value": "MouseButtonReleased"
          },
          "parameters": [
            "",
            "Left"
          ],
          "subInstructions": []
        },
        {
          "type": {
            "inverted": false,
            "value": "Timer"
          },
          "parameters": [
            "",
            "0.2",
            "\"buildselect\""
          ],
          "subInstructions": []
        },
        {
          "type": {
            "inverted": false,
            "value": "BuiltinCommonInstructions::Once"
          },
          "parameters": [],
          "subInstructions": []
        }
      ],
      "actions": [
        {
          "type": {
            "inverted": false,
            "value": "Create"
          },
          "parameters": [
            "",
            "lava01",
            "cursor2.X()+25",
            "cursor2.Y()+25",
            "\"\""
          ],
          "subInstructions": []
        },
        {
          "type": {
            "inverted": false,
            "value": "ModVarObjet"
          },
          "parameters": [
            "lava01",
            "selected",
            "=",
            "1"
          ],
          "subInstructions": []
        },
        {
          "type": {
            "inverted": false,
            "value": "Opacity"
          },
          "parameters": [
            "lava01",
            "=",
            "150"
          ],
          "subInstructions": []
        },
        {
          "type": {
            "inverted": false,
            "value": "ModVarScene"
          },
          "parameters": [
            "buildselect",
            "=",
            "1"
          ],
          "subInstructions": []
        },
        {
          "type": {
            "inverted": false,
            "value": "ResetTimer"
          },
          "parameters": [
            "",
            "\"buildselect\""
          ],
          "subInstructions": []
        }
      ],
      "events": []
    },
    {
      "disabled": false,
      "folded": false,
      "type": "BuiltinCommonInstructions::Standard",
      "conditions": [
        {
          "type": {
            "inverted": true,
            "value": "CollisionNP"
          },
          "parameters": [
            "lava01",
            "BLOCKclick",
            "",
            "",
            "yes"
          ],
          "subInstructions": []
        },
        {
          "type": {
            "inverted": false,
            "value": "VarObjet"
          },
          "parameters": [
            "lava01",
            "selected",
            "=",
            "1"
          ],
          "subInstructions": []
        },
        {
          "type": {
            "inverted": false,
            "value": "VarScene"
          },
          "parameters": [
            "buildselect",
            "=",
            "1"
          ],
          "subInstructions": []
        },
        {
          "type": {
            "inverted": false,
            "value": "Timer"
          },
          "parameters": [
            "",
            "0.2",
            "\"buildselect\""
          ],
          "subInstructions": []
        },
        {
          "type": {
            "inverted": false,
            "value": "MouseButtonReleased"
          },
          "parameters": [
            "",
            "Left"
          ],
          "subInstructions": []
        },
        {
          "type": {
            "inverted": false,
            "value": "BuiltinCommonInstructions::Once"
          },
          "parameters": [],
          "subInstructions": []
        }
      ],
      "actions": [
        {
          "type": {
            "inverted": false,
            "value": "ChangeColor"
          },
          "parameters": [
            "lava01",
            "\"255;255;255\""
          ],
          "subInstructions": []
        },
        {
          "type": {
            "inverted": false,
            "value": "Opacity"
          },
          "parameters": [
            "lava01",
            "=",
            "255"
          ],
          "subInstructions": []
        },
        {
          "type": {
            "inverted": false,
            "value": "ModVarObjet"
          },
          "parameters": [
            "lava01",
            "selected",
            "=",
            "0"
          ],
          "subInstructions": []
        },
        {
          "type": {
            "inverted": false,
            "value": "ModVarScene"
          },
          "parameters": [
            "buildselect",
            "=",
            "0"
          ],
          "subInstructions": []
        },
        {
          "type": {
            "inverted": false,
            "value": "ResetTimer"
          },
          "parameters": [
            "",
            "\"buildselect\""
          ],
          "subInstructions": []
        },
        {
          "type": {
            "inverted": false,
            "value": "PlatformBehavior::ChangePlatformType"
          },
          "parameters": [
            "lava01",
            "Platform",
            "\"Platform\""
          ],
          "subInstructions": []
        }
      ],
      "events": []
    },
    {
      "disabled": false,
      "folded": false,
      "type": "BuiltinCommonInstructions::Standard",
      "conditions": [],
      "actions": [],
      "events": []
    },
    {
      "disabled": false,
      "folded": false,
      "type": "BuiltinCommonInstructions::ForEach",
      "object": "lava01",
      "conditions": [
        {
          "type": {
            "inverted": false,
            "value": "VarObjet"
          },
          "parameters": [
            "lava01",
            "selected",
            "=",
            "1"
          ],
          "subInstructions": []
        }
      ],
      "actions": [
        {
          "type": {
            "inverted": false,
            "value": "MettreXY"
          },
          "parameters": [
            "lava01",
            "=",
            "cursor2.X()+25",
            "=",
            "cursor2.Y()+25"
          ],
          "subInstructions": []
        },
        {
          "type": {
            "inverted": false,
            "value": "PlatformBehavior::ChangePlatformType"
          },
          "parameters": [
            "lava01",
            "Platform",
            "\"Ladder\""
          ],
          "subInstructions": []
        }
      ],
      "events": []
    },
    {
      "disabled": false,
      "folded": false,
      "type": "BuiltinCommonInstructions::ForEach",
      "object": "lava01",
      "conditions": [
        {
          "type": {
            "inverted": false,
            "value": "VarObjet"
          },
          "parameters": [
            "lava01",
            "selected",
            "=",
            "1"
          ],
          "subInstructions": []
        },
        {
          "type": {
            "inverted": false,
            "value": "NbObjet"
          },
          "parameters": [
            "build_fond",
            "<",
            "1"
          ],
          "subInstructions": []
        }
      ],
      "actions": [
        {
          "type": {
            "inverted": false,
            "value": "Delete"
          },
          "parameters": [
            "lava01",
            "build_fond"
          ],
          "subInstructions": []
        },
        {
          "type": {
            "inverted": false,
            "value": "ModVarScene"
          },
          "parameters": [
            "buildselect",
            "=",
            "0"
          ],
          "subInstructions": []
        }
      ],
      "events": []
    },
    {
      "disabled": false,
      "folded": false,
      "type": "BuiltinCommonInstructions::Standard",
      "conditions": [],
      "actions": [],
      "events": []
    },
    {
      "disabled": false,
      "folded": false,
      "type": "BuiltinCommonInstructions::Standard",
      "conditions": [],
      "actions": [],
      "events": []
    },
    {
      "disabled": false,
      "folded": false,
      "type": "BuiltinCommonInstructions::Standard",
      "conditions": [],
      "actions": [],
      "events": []
    },
    {
      "disabled": false,
      "folded": false,
      "type": "BuiltinCommonInstructions::Standard",
      "conditions": [],
      "actions": [],
      "events": []
    },
    {
      "disabled": false,
      "folded": false,
      "type": "BuiltinCommonInstructions::Standard",
      "conditions": [],
      "actions": [],
      "events": []
    },
    {
      "disabled": false,
      "folded": false,
      "type": "BuiltinCommonInstructions::Standard",
      "conditions": [],
      "actions": [],
      "events": []
    },
    {
      "disabled": false,
      "folded": false,
      "type": "BuiltinCommonInstructions::Standard",
      "conditions": [],
      "actions": [],
      "events": []
    },
    {
      "disabled": false,
      "folded": false,
      "type": "BuiltinCommonInstructions::Standard",
      "conditions": [],
      "actions": [],
      "events": []
    },
    {
      "disabled": false,
      "folded": false,
      "type": "BuiltinCommonInstructions::Standard",
      "conditions": [],
      "actions": [],
      "events": []
    },
    {
      "disabled": false,
      "folded": false,
      "type": "BuiltinCommonInstructions::Standard",
      "conditions": [],
      "actions": [],
      "events": []
    },
    {
      "disabled": false,
      "folded": false,
      "type": "BuiltinCommonInstructions::Standard",
      "conditions": [],
      "actions": [],
      "events": []
    },
    {
      "disabled": false,
      "folded": false,
      "type": "BuiltinCommonInstructions::Standard",
      "conditions": [],
      "actions": [],
      "events": []
    }
  ]
}