{
  "associatedLayout": "aventure_NEW",
  "lastChangeTimeStamp": 0,
  "name": "effectblocks",
  "events": [
    {
      "disabled": false,
      "folded": false,
      "type": "BuiltinCommonInstructions::Standard",
      "conditions": [
        {
          "type": {
            "inverted": false,
            "value": "NbObjet"
          },
          "parameters": [
            "textbox_champi",
            "=",
            "0"
          ],
          "subInstructions": []
        },
        {
          "type": {
            "inverted": false,
            "value": "NbObjet"
          },
          "parameters": [
            "battleath2",
            "=",
            "0"
          ],
          "subInstructions": []
        },
        {
          "type": {
            "inverted": false,
            "value": "NbObjet"
          },
          "parameters": [
            "optiongroup",
            "=",
            "0"
          ],
          "subInstructions": []
        },
        {
          "type": {
            "inverted": false,
            "value": "NbObjet"
          },
          "parameters": [
            "maininv",
            "=",
            "0"
          ],
          "subInstructions": []
        },
        {
          "type": {
            "inverted": true,
            "value": "Visible"
          },
          "parameters": [
            "loinventoryL"
          ],
          "subInstructions": []
        },
        {
          "type": {
            "inverted": false,
            "value": "CollisionNP"
          },
          "parameters": [
            "tnticon",
            "selectorinv",
            "",
            "",
            ""
          ],
          "subInstructions": []
        },
        {
          "type": {
            "inverted": false,
            "value": "KeyFromTextPressed"
          },
          "parameters": [
            "",
            "VariableString(controlspace)"
          ],
          "subInstructions": []
        },
        {
          "type": {
            "inverted": false,
            "value": "VarGlobal"
          },
          "parameters": [
            "tnt",
            ">",
            "0"
          ],
          "subInstructions": []
        },
        {
          "type": {
            "inverted": false,
            "value": "NbObjet"
          },
          "parameters": [
            "commandGroup",
            "=",
            "0"
          ],
          "subInstructions": []
        },
        {
          "type": {
            "inverted": true,
            "value": "CollisionNP"
          },
          "parameters": [
            "cursor2",
            "tnt",
            "",
            "",
            "yes"
          ],
          "subInstructions": []
        },
        {
          "type": {
            "inverted": false,
            "value": "BuiltinCommonInstructions::Once"
          },
          "parameters": [],
          "subInstructions": []
        }
      ],
      "actions": [
        {
          "type": {
            "inverted": false,
            "value": "Create"
          },
          "parameters": [
            "",
            "tnt",
            "cursor2.X()+22",
            "cursor2.Y()+24",
            "\"\""
          ],
          "subInstructions": []
        },
        {
          "type": {
            "inverted": false,
            "value": "Create"
          },
          "parameters": [
            "",
            "tntarea",
            "cursor2.X()+22",
            "cursor2.Y()+24",
            "\"\""
          ],
          "subInstructions": []
        },
        {
          "type": {
            "inverted": false,
            "value": "LinkedObjects::LinkObjects"
          },
          "parameters": [
            "",
            "tnt",
            "tntarea"
          ],
          "subInstructions": []
        },
        {
          "type": {
            "inverted": false,
            "value": "ChangePlan"
          },
          "parameters": [
            "tnt",
            "=",
            "loeau.ZOrder()-1"
          ],
          "subInstructions": []
        },
        {
          "type": {
            "inverted": false,
            "value": "ModVarGlobal"
          },
          "parameters": [
            "tnt",
            "-",
            "1"
          ],
          "subInstructions": []
        }
      ],
      "events": []
    },
    {
      "disabled": false,
      "folded": false,
      "type": "BuiltinCommonInstructions::Standard",
      "conditions": [],
      "actions": [],
      "events": []
    },
    {
      "disabled": true,
      "folded": false,
      "type": "BuiltinCommonInstructions::ForEach",
      "object": "tnt",
      "conditions": [
        {
          "type": {
            "inverted": false,
            "value": "AnimationEnded"
          },
          "parameters": [
            "tnt"
          ],
          "subInstructions": []
        },
        {
          "type": {
            "inverted": true,
            "value": "CollisionNP"
          },
          "parameters": [
            "tntarea",
            "tnt",
            "",
            "",
            "yes"
          ],
          "subInstructions": []
        },
        {
          "type": {
            "inverted": false,
            "value": "BuiltinCommonInstructions::Once"
          },
          "parameters": [],
          "subInstructions": []
        }
      ],
      "actions": [
        {
          "type": {
            "inverted": false,
            "value": "Delete"
          },
          "parameters": [
            "tnt",
            ""
          ],
          "subInstructions": []
        }
      ],
      "events": []
    },
    {
      "disabled": true,
      "folded": false,
      "type": "BuiltinCommonInstructions::Standard",
      "conditions": [
        {
          "type": {
            "inverted": false,
            "value": "LinkedObjects::PickObjectsLinkedTo"
          },
          "parameters": [
            "",
            "tnt",
            "tntarea"
          ],
          "subInstructions": []
        },
        {
          "type": {
            "inverted": false,
            "value": "AnimationEnded"
          },
          "parameters": [
            "tnt"
          ],
          "subInstructions": []
        }
      ],
      "actions": [
        {
          "type": {
            "inverted": false,
            "value": "Delete"
          },
          "parameters": [
            "tnt",
            ""
          ],
          "subInstructions": []
        },
        {
          "type": {
            "inverted": false,
            "value": "Delete"
          },
          "parameters": [
            "tntarea",
            ""
          ],
          "subInstructions": []
        }
      ],
      "events": []
    },
    {
      "disabled": true,
      "folded": false,
      "type": "BuiltinCommonInstructions::ForEach",
      "object": "tnt",
      "conditions": [],
      "actions": [
        {
          "type": {
            "inverted": false,
            "value": "Delete"
          },
          "parameters": [
            "tnt",
            ""
          ],
          "subInstructions": []
        },
        {
          "type": {
            "inverted": false,
            "value": "Delete"
          },
          "parameters": [
            "tntarea",
            ""
          ],
          "subInstructions": []
        }
      ],
      "events": []
    },
    {
      "disabled": false,
      "folded": false,
      "type": "BuiltinCommonInstructions::ForEach",
      "object": "tntarea",
      "conditions": [
        {
          "type": {
            "inverted": false,
            "value": "CollisionNP"
          },
          "parameters": [
            "tntarea",
            "hero",
            "",
            "",
            "yes"
          ],
          "subInstructions": []
        },
        {
          "type": {
            "inverted": false,
            "value": "AnimationEnded"
          },
          "parameters": [
            "tnt"
          ],
          "subInstructions": []
        },
        {
          "type": {
            "inverted": false,
            "value": "BuiltinCommonInstructions::Once"
          },
          "parameters": [],
          "subInstructions": []
        }
      ],
      "actions": [
        {
          "type": {
            "inverted": false,
            "value": "ModVarGlobal"
          },
          "parameters": [
            "hp",
            "-",
            "round(GlobalVariable(lvl)*10)"
          ],
          "subInstructions": []
        },
        {
          "type": {
            "inverted": false,
            "value": "PlaySoundCanal"
          },
          "parameters": [
            "",
            "song\\sounds\\hit.ogg",
            "2",
            "Variable(sound)",
            "Variable(channelavaible)",
            ""
          ],
          "subInstructions": []
        },
        {
          "type": {
            "inverted": false,
            "value": "ModVarScene"
          },
          "parameters": [
            "hithero",
            "=",
            "3"
          ],
          "subInstructions": []
        },
        {
          "type": {
            "inverted": false,
            "value": "ResetTimer"
          },
          "parameters": [
            "",
            "\"heal8\""
          ],
          "subInstructions": []
        }
      ],
      "events": []
    },
    {
      "disabled": false,
      "folded": false,
      "type": "BuiltinCommonInstructions::ForEach",
      "object": "tntarea",
      "conditions": [
        {
          "type": {
            "inverted": false,
            "value": "AnimationEnded"
          },
          "parameters": [
            "tnt"
          ],
          "subInstructions": []
        },
        {
          "type": {
            "inverted": false,
            "value": "CollisionNP"
          },
          "parameters": [
            "tntarea",
            "tnt",
            "",
            "",
            "yes"
          ],
          "subInstructions": []
        }
      ],
      "actions": [
        {
          "type": {
            "inverted": false,
            "value": "Create"
          },
          "parameters": [
            "",
            "explosion",
            "tnt.X()",
            "tnt.Y()",
            "\"\""
          ],
          "subInstructions": []
        },
        {
          "type": {
            "inverted": false,
            "value": "Delete"
          },
          "parameters": [
            "tnt",
            ""
          ],
          "subInstructions": []
        },
        {
          "type": {
            "inverted": false,
            "value": "Delete"
          },
          "parameters": [
            "tntarea",
            ""
          ],
          "subInstructions": []
        }
      ],
      "events": []
    },
    {
      "disabled": false,
      "folded": false,
      "type": "BuiltinCommonInstructions::ForEach",
      "object": "tntarea",
      "conditions": [
        {
          "type": {
            "inverted": true,
            "value": "CollisionNP"
          },
          "parameters": [
            "tntarea",
            "tnt",
            "",
            "",
            "yes"
          ],
          "subInstructions": []
        },
        {
          "type": {
            "inverted": false,
            "value": "BuiltinCommonInstructions::Once"
          },
          "parameters": [],
          "subInstructions": []
        }
      ],
      "actions": [
        {
          "type": {
            "inverted": false,
            "value": "Delete"
          },
          "parameters": [
            "tntarea",
            ""
          ],
          "subInstructions": []
        }
      ],
      "events": []
    },
    {
      "disabled": true,
      "folded": false,
      "type": "BuiltinCommonInstructions::ForEach",
      "object": "tntarea",
      "conditions": [
        {
          "type": {
            "inverted": false,
            "value": "AnimationEnded"
          },
          "parameters": [
            "tnt"
          ],
          "subInstructions": []
        }
      ],
      "actions": [
        {
          "type": {
            "inverted": false,
            "value": "Create"
          },
          "parameters": [
            "",
            "explosion",
            "tnt.X()",
            "tnt.Y()",
            "\"\""
          ],
          "subInstructions": []
        },
        {
          "type": {
            "inverted": false,
            "value": "Opacity"
          },
          "parameters": [
            "tntarea",
            "=",
            "122.5"
          ],
          "subInstructions": []
        },
        {
          "type": {
            "inverted": false,
            "value": "Delete"
          },
          "parameters": [
            "tnt",
            ""
          ],
          "subInstructions": []
        }
      ],
      "events": []
    },
    {
      "disabled": false,
      "folded": false,
      "type": "BuiltinCommonInstructions::Standard",
      "conditions": [],
      "actions": [],
      "events": []
    },
    {
      "disabled": true,
      "folded": false,
      "type": "BuiltinCommonInstructions::Standard",
      "conditions": [
        {
          "type": {
            "inverted": false,
            "value": "CollisionNP"
          },
          "parameters": [
            "explosion",
            "monsters",
            "",
            "",
            ""
          ],
          "subInstructions": []
        },
        {
          "type": {
            "inverted": false,
            "value": "BuiltinCommonInstructions::Once"
          },
          "parameters": [],
          "subInstructions": []
        }
      ],
      "actions": [
        {
          "type": {
            "inverted": false,
            "value": "ModVarObjet"
          },
          "parameters": [
            "hpbarblop2",
            "hp",
            "-",
            "100"
          ],
          "subInstructions": []
        },
        {
          "type": {
            "inverted": false,
            "value": "Delete"
          },
          "parameters": [
            "tntarea",
            ""
          ],
          "subInstructions": []
        }
      ],
      "events": []
    },
    {
      "disabled": false,
      "folded": false,
      "type": "BuiltinCommonInstructions::Standard",
      "conditions": [],
      "actions": [],
      "events": []
    },
    {
      "disabled": false,
      "folded": false,
      "type": "BuiltinCommonInstructions::Standard",
      "conditions": [],
      "actions": [],
      "events": []
    },
    {
      "disabled": false,
      "folded": false,
      "type": "BuiltinCommonInstructions::Standard",
      "conditions": [],
      "actions": [],
      "events": []
    },
    {
      "disabled": false,
      "folded": false,
      "type": "BuiltinCommonInstructions::Standard",
      "conditions": [],
      "actions": [],
      "events": []
    },
    {
      "disabled": false,
      "folded": false,
      "type": "BuiltinCommonInstructions::Standard",
      "conditions": [],
      "actions": [],
      "events": []
    },
    {
      "disabled": false,
      "folded": false,
      "type": "BuiltinCommonInstructions::Standard",
      "conditions": [
        {
          "type": {
            "inverted": false,
            "value": "NbObjet"
          },
          "parameters": [
            "textbox_champi",
            "=",
            "0"
          ],
          "subInstructions": []
        },
        {
          "type": {
            "inverted": false,
            "value": "NbObjet"
          },
          "parameters": [
            "battleath2",
            "=",
            "0"
          ],
          "subInstructions": []
        },
        {
          "type": {
            "inverted": false,
            "value": "NbObjet"
          },
          "parameters": [
            "optiongroup",
            "=",
            "0"
          ],
          "subInstructions": []
        },
        {
          "type": {
            "inverted": false,
            "value": "NbObjet"
          },
          "parameters": [
            "maininv",
            "=",
            "0"
          ],
          "subInstructions": []
        },
        {
          "type": {
            "inverted": true,
            "value": "Visible"
          },
          "parameters": [
            "loinventoryL"
          ],
          "subInstructions": []
        },
        {
          "type": {
            "inverted": false,
            "value": "CollisionNP"
          },
          "parameters": [
            "lo4icon",
            "selectorinv",
            "",
            "",
            ""
          ],
          "subInstructions": []
        },
        {
          "type": {
            "inverted": false,
            "value": "KeyFromTextPressed"
          },
          "parameters": [
            "",
            "VariableString(controlspace)"
          ],
          "subInstructions": []
        },
        {
          "type": {
            "inverted": false,
            "value": "VarGlobal"
          },
          "parameters": [
            "poison",
            ">",
            "0"
          ],
          "subInstructions": []
        },
        {
          "type": {
            "inverted": false,
            "value": "BuiltinCommonInstructions::Once"
          },
          "parameters": [],
          "subInstructions": []
        },
        {
          "type": {
            "inverted": false,
            "value": "NbObjet"
          },
          "parameters": [
            "commandGroup",
            "=",
            "0"
          ],
          "subInstructions": []
        }
      ],
      "actions": [
        {
          "type": {
            "inverted": false,
            "value": "Create"
          },
          "parameters": [
            "lo3",
            "attack",
            "cursor2.X()",
            "cursor2.Y()",
            ""
          ],
          "subInstructions": []
        },
        {
          "type": {
            "inverted": false,
            "value": "Opacity"
          },
          "parameters": [
            "attack",
            "=",
            "100"
          ],
          "subInstructions": []
        },
        {
          "type": {
            "inverted": false,
            "value": "ChangePlan"
          },
          "parameters": [
            "attack",
            "=",
            "80"
          ],
          "subInstructions": []
        },
        {
          "type": {
            "inverted": false,
            "value": "ModVarScene"
          },
          "parameters": [
            "currentattack",
            "=",
            "0.05"
          ],
          "subInstructions": []
        },
        {
          "type": {
            "inverted": false,
            "value": "ModVarGlobal"
          },
          "parameters": [
            "poison",
            "-",
            "1"
          ],
          "subInstructions": []
        },
        {
          "type": {
            "inverted": false,
            "value": "ResetTimer"
          },
          "parameters": [
            "",
            "\"zonepoison\""
          ],
          "subInstructions": []
        }
      ],
      "events": []
    },
    {
      "disabled": false,
      "folded": false,
      "type": "BuiltinCommonInstructions::Standard",
      "conditions": [],
      "actions": [],
      "events": []
    },
    {
      "disabled": false,
      "folded": false,
      "type": "BuiltinCommonInstructions::Standard",
      "conditions": [],
      "actions": [],
      "events": []
    },
    {
      "disabled": false,
      "folded": false,
      "type": "BuiltinCommonInstructions::Standard",
      "conditions": [],
      "actions": [],
      "events": []
    },
    {
      "disabled": false,
      "folded": false,
      "type": "BuiltinCommonInstructions::Standard",
      "conditions": [],
      "actions": [],
      "events": []
    },
    {
      "disabled": false,
      "folded": false,
      "type": "BuiltinCommonInstructions::Standard",
      "conditions": [],
      "actions": [],
      "events": []
    },
    {
      "disabled": false,
      "folded": false,
      "type": "BuiltinCommonInstructions::Standard",
      "conditions": [],
      "actions": [],
      "events": []
    },
    {
      "disabled": false,
      "folded": false,
      "type": "BuiltinCommonInstructions::ForEach",
      "object": "attack",
      "conditions": [
        {
          "type": {
            "inverted": false,
            "value": "VarObjet"
          },
          "parameters": [
            "attack",
            "time",
            "=",
            "0"
          ],
          "subInstructions": []
        },
        {
          "type": {
            "inverted": false,
            "value": "BuiltinCommonInstructions::Once"
          },
          "parameters": [],
          "subInstructions": []
        }
      ],
      "actions": [
        {
          "type": {
            "inverted": false,
            "value": "ModVarObjet"
          },
          "parameters": [
            "attack",
            "time",
            "=",
            "1"
          ],
          "subInstructions": []
        },
        {
          "type": {
            "inverted": false,
            "value": "ResetObjectTimer"
          },
          "parameters": [
            "attack",
            "\"time\""
          ],
          "subInstructions": []
        }
      ],
      "events": []
    },
    {
      "disabled": false,
      "folded": false,
      "type": "BuiltinCommonInstructions::Standard",
      "conditions": [],
      "actions": [],
      "events": []
    },
    {
      "disabled": false,
      "folded": false,
      "type": "BuiltinCommonInstructions::ForEach",
      "object": "attack",
      "conditions": [
        {
          "type": {
            "inverted": false,
            "value": "VarObjet"
          },
          "parameters": [
            "attack",
            "time",
            "=",
            "1"
          ],
          "subInstructions": []
        },
        {
          "type": {
            "inverted": false,
            "value": "ObjectTimer"
          },
          "parameters": [
            "attack",
            "\"time\"",
            "3"
          ],
          "subInstructions": []
        },
        {
          "type": {
            "inverted": false,
            "value": "BuiltinCommonInstructions::Once"
          },
          "parameters": [],
          "subInstructions": []
        }
      ],
      "actions": [
        {
          "type": {
            "inverted": false,
            "value": "ChangeAnimation"
          },
          "parameters": [
            "attack",
            "=",
            "1"
          ],
          "subInstructions": []
        },
        {
          "type": {
            "inverted": false,
            "value": "ModVarObjet"
          },
          "parameters": [
            "attack",
            "time",
            "=",
            "2"
          ],
          "subInstructions": []
        }
      ],
      "events": []
    },
    {
      "disabled": false,
      "folded": false,
      "type": "BuiltinCommonInstructions::Standard",
      "conditions": [],
      "actions": [],
      "events": []
    },
    {
      "disabled": false,
      "folded": false,
      "type": "BuiltinCommonInstructions::Standard",
      "conditions": [],
      "actions": [],
      "events": []
    },
    {
      "disabled": false,
      "folded": false,
      "type": "BuiltinCommonInstructions::Standard",
      "conditions": [],
      "actions": [],
      "events": []
    },
    {
      "disabled": false,
      "folded": false,
      "type": "BuiltinCommonInstructions::Standard",
      "conditions": [],
      "actions": [],
      "events": []
    },
    {
      "disabled": false,
      "folded": false,
      "type": "BuiltinCommonInstructions::ForEach",
      "object": "attack",
      "conditions": [
        {
          "type": {
            "inverted": false,
            "value": "Animation"
          },
          "parameters": [
            "attack",
            "=",
            "1"
          ],
          "subInstructions": []
        },
        {
          "type": {
            "inverted": false,
            "value": "AnimationEnded"
          },
          "parameters": [
            "attack"
          ],
          "subInstructions": []
        }
      ],
      "actions": [
        {
          "type": {
            "inverted": false,
            "value": "Delete"
          },
          "parameters": [
            "attack",
            ""
          ],
          "subInstructions": []
        }
      ],
      "events": []
    },
    {
      "disabled": false,
      "folded": false,
      "type": "BuiltinCommonInstructions::Standard",
      "conditions": [],
      "actions": [],
      "events": []
    },
    {
      "disabled": false,
      "folded": false,
      "type": "BuiltinCommonInstructions::Standard",
      "conditions": [],
      "actions": [],
      "events": []
    },
    {
      "disabled": true,
      "folded": false,
      "type": "BuiltinCommonInstructions::ForEach",
      "object": "attack",
      "conditions": [
        {
          "type": {
            "inverted": false,
            "value": "Animation"
          },
          "parameters": [
            "attack",
            "=",
            "0"
          ],
          "subInstructions": []
        },
        {
          "type": {
            "inverted": false,
            "value": "AnimationEnded"
          },
          "parameters": [
            "attack"
          ],
          "subInstructions": []
        },
        {
          "type": {
            "inverted": false,
            "value": "VarObjet"
          },
          "parameters": [
            "attack",
            "attack",
            ">=",
            "8"
          ],
          "subInstructions": []
        },
        {
          "type": {
            "inverted": false,
            "value": "BuiltinCommonInstructions::Once"
          },
          "parameters": [],
          "subInstructions": []
        }
      ],
      "actions": [
        {
          "type": {
            "inverted": false,
            "value": "ChangeAnimation"
          },
          "parameters": [
            "attack",
            "=",
            "1"
          ],
          "subInstructions": []
        }
      ],
      "events": []
    },
    {
      "disabled": true,
      "folded": false,
      "type": "BuiltinCommonInstructions::ForEach",
      "object": "attack",
      "conditions": [
        {
          "type": {
            "inverted": false,
            "value": "Timer"
          },
          "parameters": [
            "",
            "1",
            "\"zonepoison\""
          ],
          "subInstructions": []
        },
        {
          "type": {
            "inverted": false,
            "value": "BuiltinCommonInstructions::Once"
          },
          "parameters": [],
          "subInstructions": []
        }
      ],
      "actions": [
        {
          "type": {
            "inverted": false,
            "value": "ModVarObjet"
          },
          "parameters": [
            "attack",
            "attack",
            "+",
            "1"
          ],
          "subInstructions": []
        }
      ],
      "events": []
    },
    {
      "disabled": false,
      "folded": false,
      "type": "BuiltinCommonInstructions::Standard",
      "conditions": [],
      "actions": [],
      "events": []
    },
    {
      "disabled": false,
      "folded": false,
      "type": "BuiltinCommonInstructions::Standard",
      "conditions": [],
      "actions": [],
      "events": []
    },
    {
      "disabled": false,
      "folded": false,
      "type": "BuiltinCommonInstructions::ForEach",
      "object": "heal",
      "conditions": [
        {
          "type": {
            "inverted": false,
            "value": "AnimationEnded"
          },
          "parameters": [
            "heal"
          ],
          "subInstructions": []
        },
        {
          "type": {
            "inverted": false,
            "value": "Animation"
          },
          "parameters": [
            "heal",
            "=",
            "1"
          ],
          "subInstructions": []
        }
      ],
      "actions": [
        {
          "type": {
            "inverted": false,
            "value": "Delete"
          },
          "parameters": [
            "heal",
            "heal"
          ],
          "subInstructions": []
        }
      ],
      "events": []
    },
    {
      "disabled": false,
      "folded": false,
      "type": "BuiltinCommonInstructions::Standard",
      "conditions": [
        {
          "type": {
            "inverted": false,
            "value": "NbObjet"
          },
          "parameters": [
            "textbox_champi",
            "=",
            "0"
          ],
          "subInstructions": []
        },
        {
          "type": {
            "inverted": false,
            "value": "NbObjet"
          },
          "parameters": [
            "battleath2",
            "=",
            "0"
          ],
          "subInstructions": []
        },
        {
          "type": {
            "inverted": false,
            "value": "NbObjet"
          },
          "parameters": [
            "optiongroup",
            "=",
            "0"
          ],
          "subInstructions": []
        },
        {
          "type": {
            "inverted": false,
            "value": "NbObjet"
          },
          "parameters": [
            "maininv",
            "=",
            "0"
          ],
          "subInstructions": []
        },
        {
          "type": {
            "inverted": true,
            "value": "Visible"
          },
          "parameters": [
            "loinventoryL"
          ],
          "subInstructions": []
        },
        {
          "type": {
            "inverted": false,
            "value": "CollisionNP"
          },
          "parameters": [
            "healicon",
            "selectorinv",
            "",
            "",
            ""
          ],
          "subInstructions": []
        },
        {
          "type": {
            "inverted": true,
            "value": "CollisionNP"
          },
          "parameters": [
            "cursor2",
            "heal",
            "",
            "",
            "yes"
          ],
          "subInstructions": []
        },
        {
          "type": {
            "inverted": false,
            "value": "KeyFromTextPressed"
          },
          "parameters": [
            "",
            "VariableString(controlspace)"
          ],
          "subInstructions": []
        },
        {
          "type": {
            "inverted": false,
            "value": "VarGlobal"
          },
          "parameters": [
            "heal",
            ">",
            "0"
          ],
          "subInstructions": []
        },
        {
          "type": {
            "inverted": false,
            "value": "NbObjet"
          },
          "parameters": [
            "commandGroup",
            "=",
            "0"
          ],
          "subInstructions": []
        },
        {
          "type": {
            "inverted": false,
            "value": "BuiltinCommonInstructions::Once"
          },
          "parameters": [],
          "subInstructions": []
        }
      ],
      "actions": [
        {
          "type": {
            "inverted": false,
            "value": "Create"
          },
          "parameters": [
            "lo3",
            "heal",
            "cursor2.X()",
            "cursor2.Y()",
            ""
          ],
          "subInstructions": []
        },
        {
          "type": {
            "inverted": false,
            "value": "ChangePlan"
          },
          "parameters": [
            "heal",
            "=",
            "hero.ZOrder()+1"
          ],
          "subInstructions": []
        },
        {
          "type": {
            "inverted": false,
            "value": "ModVarGlobal"
          },
          "parameters": [
            "heal",
            "-",
            "1"
          ],
          "subInstructions": []
        },
        {
          "type": {
            "inverted": false,
            "value": "ResetTimer"
          },
          "parameters": [
            "",
            "\"heal8\""
          ],
          "subInstructions": []
        }
      ],
      "events": []
    },
    {
      "disabled": false,
      "folded": false,
      "type": "BuiltinCommonInstructions::Standard",
      "conditions": [],
      "actions": [],
      "events": []
    },
    {
      "disabled": false,
      "folded": false,
      "type": "BuiltinCommonInstructions::ForEach",
      "object": "heal",
      "conditions": [
        {
          "type": {
            "inverted": false,
            "value": "VarObjet"
          },
          "parameters": [
            "heal",
            "time",
            "=",
            "1"
          ],
          "subInstructions": []
        },
        {
          "type": {
            "inverted": false,
            "value": "ObjectTimer"
          },
          "parameters": [
            "heal",
            "\"time\"",
            "3"
          ],
          "subInstructions": []
        },
        {
          "type": {
            "inverted": false,
            "value": "BuiltinCommonInstructions::Once"
          },
          "parameters": [],
          "subInstructions": []
        }
      ],
      "actions": [
        {
          "type": {
            "inverted": false,
            "value": "ChangeAnimation"
          },
          "parameters": [
            "heal",
            "=",
            "1"
          ],
          "subInstructions": []
        },
        {
          "type": {
            "inverted": false,
            "value": "ModVarObjet"
          },
          "parameters": [
            "heal",
            "time",
            "=",
            "2"
          ],
          "subInstructions": []
        }
      ],
      "events": []
    },
    {
      "disabled": false,
      "folded": false,
      "type": "BuiltinCommonInstructions::ForEach",
      "object": "heal",
      "conditions": [
        {
          "type": {
            "inverted": false,
            "value": "VarObjet"
          },
          "parameters": [
            "heal",
            "time",
            "=",
            "0"
          ],
          "subInstructions": []
        },
        {
          "type": {
            "inverted": false,
            "value": "BuiltinCommonInstructions::Once"
          },
          "parameters": [],
          "subInstructions": []
        }
      ],
      "actions": [
        {
          "type": {
            "inverted": false,
            "value": "ModVarObjet"
          },
          "parameters": [
            "heal",
            "time",
            "=",
            "1"
          ],
          "subInstructions": []
        },
        {
          "type": {
            "inverted": false,
            "value": "ResetObjectTimer"
          },
          "parameters": [
            "heal",
            "\"time\""
          ],
          "subInstructions": []
        }
      ],
      "events": []
    },
    {
      "disabled": false,
      "folded": false,
      "type": "BuiltinCommonInstructions::Standard",
      "conditions": [],
      "actions": [],
      "events": []
    },
    {
      "disabled": false,
      "folded": false,
      "type": "BuiltinCommonInstructions::Standard",
      "conditions": [],
      "actions": [],
      "events": []
    },
    {
      "disabled": false,
      "folded": false,
      "type": "BuiltinCommonInstructions::Standard",
      "conditions": [],
      "actions": [],
      "events": []
    },
    {
      "disabled": false,
      "folded": false,
      "type": "BuiltinCommonInstructions::Standard",
      "conditions": [],
      "actions": [],
      "events": []
    },
    {
      "disabled": false,
      "folded": false,
      "type": "BuiltinCommonInstructions::Standard",
      "conditions": [],
      "actions": [],
      "events": []
    },
    {
      "disabled": false,
      "folded": false,
      "type": "BuiltinCommonInstructions::Standard",
      "conditions": [],
      "actions": [],
      "events": []
    },
    {
      "disabled": false,
      "folded": false,
      "type": "BuiltinCommonInstructions::Comment",
      "color": {
        "b": 109,
        "g": 230,
        "r": 255,
        "textB": 0,
        "textG": 0,
        "textR": 0
      },
      "comment": "",
      "comment2": ""
    },
    {
      "disabled": false,
      "folded": false,
      "type": "BuiltinCommonInstructions::Standard",
      "conditions": [],
      "actions": [],
      "events": []
    },
    {
      "disabled": false,
      "folded": false,
      "type": "BuiltinCommonInstructions::Standard",
      "conditions": [],
      "actions": [],
      "events": []
    },
    {
      "disabled": false,
      "folded": false,
      "type": "BuiltinCommonInstructions::Standard",
      "conditions": [],
      "actions": [],
      "events": []
    },
    {
      "disabled": false,
      "folded": false,
      "type": "BuiltinCommonInstructions::ForEach",
      "object": "heal",
      "conditions": [
        {
          "type": {
            "inverted": false,
            "value": "CollisionNP"
          },
          "parameters": [
            "heal",
            "hero",
            "",
            "",
            ""
          ],
          "subInstructions": []
        },
        {
          "type": {
            "inverted": false,
            "value": "VarGlobal"
          },
          "parameters": [
            "hp",
            "<",
            "100"
          ],
          "subInstructions": []
        },
        {
          "type": {
            "inverted": false,
            "value": "Timer"
          },
          "parameters": [
            "",
            "0.05",
            "\"heal8\""
          ],
          "subInstructions": []
        }
      ],
      "actions": [
        {
          "type": {
            "inverted": false,
            "value": "ModVarGlobal"
          },
          "parameters": [
            "hp",
            "+",
            "1"
          ],
          "subInstructions": []
        },
        {
          "type": {
            "inverted": false,
            "value": "PlaySoundCanal"
          },
          "parameters": [
            "",
            "song\\sounds\\heal.ogg",
            "Variable(channelavaible)",
            "Variable(sound)",
            "Variable(sound)",
            ""
          ],
          "subInstructions": []
        },
        {
          "type": {
            "inverted": false,
            "value": "ModVarScene"
          },
          "parameters": [
            "hithero",
            "=",
            "2"
          ],
          "subInstructions": []
        },
        {
          "type": {
            "inverted": false,
            "value": "ResetTimer"
          },
          "parameters": [
            "",
            "\"heal8\""
          ],
          "subInstructions": []
        }
      ],
      "events": []
    },
    {
      "disabled": false,
      "folded": false,
      "type": "BuiltinCommonInstructions::Standard",
      "conditions": [],
      "actions": [],
      "events": []
    },
    {
      "disabled": false,
      "folded": false,
      "type": "BuiltinCommonInstructions::Standard",
      "conditions": [],
      "actions": [],
      "events": []
    },
    {
      "disabled": false,
      "folded": false,
      "type": "BuiltinCommonInstructions::Standard",
      "conditions": [],
      "actions": [],
      "events": []
    },
    {
      "disabled": false,
      "folded": false,
      "type": "BuiltinCommonInstructions::Standard",
      "conditions": [],
      "actions": [],
      "events": []
    },
    {
      "disabled": false,
      "folded": false,
      "type": "BuiltinCommonInstructions::Standard",
      "conditions": [],
      "actions": [],
      "events": []
    },
    {
      "disabled": false,
      "folded": false,
      "type": "BuiltinCommonInstructions::Comment",
      "color": {
        "b": 109,
        "g": 230,
        "r": 255,
        "textB": 0,
        "textG": 0,
        "textR": 0
      },
      "comment": "",
      "comment2": ""
    },
    {
      "disabled": false,
      "folded": false,
      "type": "BuiltinCommonInstructions::Standard",
      "conditions": [],
      "actions": [],
      "events": []
    },
    {
      "disabled": false,
      "folded": false,
      "type": "BuiltinCommonInstructions::Standard",
      "conditions": [],
      "actions": [],
      "events": []
    },
    {
      "disabled": false,
      "folded": false,
      "type": "BuiltinCommonInstructions::Standard",
      "conditions": [
        {
          "type": {
            "inverted": false,
            "value": "NbObjet"
          },
          "parameters": [
            "textbox_champi",
            "=",
            "0"
          ],
          "subInstructions": []
        },
        {
          "type": {
            "inverted": false,
            "value": "NbObjet"
          },
          "parameters": [
            "battleath2",
            "=",
            "0"
          ],
          "subInstructions": []
        },
        {
          "type": {
            "inverted": false,
            "value": "NbObjet"
          },
          "parameters": [
            "optiongroup",
            "=",
            "0"
          ],
          "subInstructions": []
        },
        {
          "type": {
            "inverted": false,
            "value": "NbObjet"
          },
          "parameters": [
            "maininv",
            "=",
            "0"
          ],
          "subInstructions": []
        },
        {
          "type": {
            "inverted": true,
            "value": "Visible"
          },
          "parameters": [
            "loinventoryL"
          ],
          "subInstructions": []
        },
        {
          "type": {
            "inverted": true,
            "value": "CollisionNP"
          },
          "parameters": [
            "cursor2",
            "BLOCKclick",
            "",
            "",
            "yes"
          ],
          "subInstructions": []
        },
        {
          "type": {
            "inverted": false,
            "value": "CollisionNP"
          },
          "parameters": [
            "herbe01icon",
            "selectorinv",
            "",
            "",
            ""
          ],
          "subInstructions": []
        },
        {
          "type": {
            "inverted": false,
            "value": "KeyFromTextPressed"
          },
          "parameters": [
            "",
            "VariableString(controlspace)"
          ],
          "subInstructions": []
        },
        {
          "type": {
            "inverted": false,
            "value": "VarGlobal"
          },
          "parameters": [
            "dirt",
            ">",
            "0"
          ],
          "subInstructions": []
        },
        {
          "type": {
            "inverted": false,
            "value": "NbObjet"
          },
          "parameters": [
            "commandGroup",
            "=",
            "0"
          ],
          "subInstructions": []
        }
      ],
      "actions": [
        {
          "type": {
            "inverted": false,
            "value": "Create"
          },
          "parameters": [
            "",
            "terre01",
            "cursor2.X()",
            "cursor2.Y()",
            "\"\""
          ],
          "subInstructions": []
        },
        {
          "type": {
            "inverted": false,
            "value": "ModVarGlobal"
          },
          "parameters": [
            "dirt",
            "-",
            "1"
          ],
          "subInstructions": []
        }
      ],
      "events": []
    },
    {
      "disabled": true,
      "folded": false,
      "type": "BuiltinCommonInstructions::Standard",
      "conditions": [
        {
          "type": {
            "inverted": false,
            "value": "NbObjet"
          },
          "parameters": [
            "battleath2",
            "=",
            "0"
          ],
          "subInstructions": []
        },
        {
          "type": {
            "inverted": false,
            "value": "NbObjet"
          },
          "parameters": [
            "optiongroup",
            "=",
            "0"
          ],
          "subInstructions": []
        },
        {
          "type": {
            "inverted": false,
            "value": "NbObjet"
          },
          "parameters": [
            "loeau2",
            "<",
            "100"
          ],
          "subInstructions": []
        },
        {
          "type": {
            "inverted": false,
            "value": "NbObjet"
          },
          "parameters": [
            "maininv",
            "=",
            "0"
          ],
          "subInstructions": []
        },
        {
          "type": {
            "inverted": true,
            "value": "Visible"
          },
          "parameters": [
            "loinventoryL"
          ],
          "subInstructions": []
        },
        {
          "type": {
            "inverted": true,
            "value": "CollisionNP"
          },
          "parameters": [
            "cursor2",
            "BLOCKclick",
            "",
            "",
            "yes"
          ],
          "subInstructions": []
        },
        {
          "type": {
            "inverted": false,
            "value": "KeyReleased"
          },
          "parameters": [
            "",
            "h"
          ],
          "subInstructions": []
        },
        {
          "type": {
            "inverted": false,
            "value": "BuiltinCommonInstructions::Once"
          },
          "parameters": [],
          "subInstructions": []
        }
      ],
      "actions": [
        {
          "type": {
            "inverted": false,
            "value": "Create"
          },
          "parameters": [
            "",
            "loeau2",
            "cursor2.X()",
            "cursor2.Y()",
            "\"\""
          ],
          "subInstructions": []
        }
      ],
      "events": []
    },
    {
      "disabled": false,
      "folded": false,
      "type": "BuiltinCommonInstructions::Standard",
      "conditions": [
        {
          "type": {
            "inverted": false,
            "value": "NbObjet"
          },
          "parameters": [
            "textbox_champi",
            "=",
            "0"
          ],
          "subInstructions": []
        },
        {
          "type": {
            "inverted": false,
            "value": "NbObjet"
          },
          "parameters": [
            "battleath2",
            "=",
            "0"
          ],
          "subInstructions": []
        },
        {
          "type": {
            "inverted": false,
            "value": "NbObjet"
          },
          "parameters": [
            "optiongroup",
            "=",
            "0"
          ],
          "subInstructions": []
        },
        {
          "type": {
            "inverted": false,
            "value": "NbObjet"
          },
          "parameters": [
            "maininv",
            "=",
            "0"
          ],
          "subInstructions": []
        },
        {
          "type": {
            "inverted": true,
            "value": "Visible"
          },
          "parameters": [
            "loinventoryL"
          ],
          "subInstructions": []
        },
        {
          "type": {
            "inverted": true,
            "value": "CollisionNP"
          },
          "parameters": [
            "cursor2",
            "BLOCKclick",
            "",
            "",
            "yes"
          ],
          "subInstructions": []
        },
        {
          "type": {
            "inverted": true,
            "value": "CollisionNP"
          },
          "parameters": [
            "cursor2",
            "mod",
            "",
            "",
            "yes"
          ],
          "subInstructions": []
        },
        {
          "type": {
            "inverted": false,
            "value": "CollisionNP"
          },
          "parameters": [
            "modicon",
            "selectorinv",
            "",
            "",
            ""
          ],
          "subInstructions": []
        },
        {
          "type": {
            "inverted": false,
            "value": "KeyFromTextPressed"
          },
          "parameters": [
            "",
            "VariableString(controlspace)"
          ],
          "subInstructions": []
        },
        {
          "type": {
            "inverted": false,
            "value": "VarGlobal"
          },
          "parameters": [
            "mod",
            ">",
            "0"
          ],
          "subInstructions": []
        },
        {
          "type": {
            "inverted": false,
            "value": "NbObjet"
          },
          "parameters": [
            "commandGroup",
            "=",
            "0"
          ],
          "subInstructions": []
        }
      ],
      "actions": [
        {
          "type": {
            "inverted": false,
            "value": "Create"
          },
          "parameters": [
            "",
            "mod",
            "cursor2.X()",
            "cursor2.Y()",
            "\"\""
          ],
          "subInstructions": []
        },
        {
          "type": {
            "inverted": false,
            "value": "ChangePlan"
          },
          "parameters": [
            "mod",
            "=",
            "5"
          ],
          "subInstructions": []
        },
        {
          "type": {
            "inverted": false,
            "value": "ModVarGlobal"
          },
          "parameters": [
            "mod",
            "-",
            "1"
          ],
          "subInstructions": []
        }
      ],
      "events": []
    },
    {
      "disabled": false,
      "folded": false,
      "type": "BuiltinCommonInstructions::Standard",
      "conditions": [],
      "actions": [],
      "events": []
    },
    {
      "disabled": false,
      "folded": false,
      "type": "BuiltinCommonInstructions::Standard",
      "conditions": [
        {
          "type": {
            "inverted": false,
            "value": "NbObjet"
          },
          "parameters": [
            "textbox_champi",
            "=",
            "0"
          ],
          "subInstructions": []
        },
        {
          "type": {
            "inverted": false,
            "value": "NbObjet"
          },
          "parameters": [
            "battleath2",
            "=",
            "0"
          ],
          "subInstructions": []
        },
        {
          "type": {
            "inverted": false,
            "value": "NbObjet"
          },
          "parameters": [
            "optiongroup",
            "=",
            "0"
          ],
          "subInstructions": []
        },
        {
          "type": {
            "inverted": false,
            "value": "NbObjet"
          },
          "parameters": [
            "maininv",
            "=",
            "0"
          ],
          "subInstructions": []
        },
        {
          "type": {
            "inverted": true,
            "value": "Visible"
          },
          "parameters": [
            "loinventoryL"
          ],
          "subInstructions": []
        },
        {
          "type": {
            "inverted": true,
            "value": "CollisionNP"
          },
          "parameters": [
            "cursor2",
            "BLOCKclick",
            "",
            "",
            "yes"
          ],
          "subInstructions": []
        },
        {
          "type": {
            "inverted": true,
            "value": "CollisionNP"
          },
          "parameters": [
            "cursor2",
            "bomb",
            "",
            "",
            "yes"
          ],
          "subInstructions": []
        },
        {
          "type": {
            "inverted": false,
            "value": "CollisionNP"
          },
          "parameters": [
            "bombicon",
            "selectorinv",
            "",
            "",
            ""
          ],
          "subInstructions": []
        },
        {
          "type": {
            "inverted": false,
            "value": "KeyFromTextPressed"
          },
          "parameters": [
            "",
            "VariableString(controlspace)"
          ],
          "subInstructions": []
        },
        {
          "type": {
            "inverted": false,
            "value": "VarGlobal"
          },
          "parameters": [
            "bomb",
            ">",
            "0"
          ],
          "subInstructions": []
        },
        {
          "type": {
            "inverted": false,
            "value": "NbObjet"
          },
          "parameters": [
            "commandGroup",
            "=",
            "0"
          ],
          "subInstructions": []
        }
      ],
      "actions": [
        {
          "type": {
            "inverted": false,
            "value": "Create"
          },
          "parameters": [
            "",
            "bomb",
            "cursor2.X()",
            "cursor2.Y()",
            "\"\""
          ],
          "subInstructions": []
        },
        {
          "type": {
            "inverted": false,
            "value": "ChangePlan"
          },
          "parameters": [
            "bomb",
            "=",
            "5"
          ],
          "subInstructions": []
        },
        {
          "type": {
            "inverted": false,
            "value": "ModVarGlobal"
          },
          "parameters": [
            "bomb",
            "-",
            "1"
          ],
          "subInstructions": []
        }
      ],
      "events": []
    },
    {
      "disabled": false,
      "folded": false,
      "type": "BuiltinCommonInstructions::Standard",
      "conditions": [],
      "actions": [],
      "events": []
    },
    {
      "disabled": false,
      "folded": false,
      "type": "BuiltinCommonInstructions::Standard",
      "conditions": [],
      "actions": [],
      "events": []
    },
    {
      "disabled": false,
      "folded": false,
      "type": "BuiltinCommonInstructions::ForEach",
      "object": "bomb",
      "conditions": [
        {
          "type": {
            "inverted": false,
            "value": "AnimationEnded"
          },
          "parameters": [
            "bomb"
          ],
          "subInstructions": []
        },
        {
          "type": {
            "inverted": false,
            "value": "BuiltinCommonInstructions::Once"
          },
          "parameters": [],
          "subInstructions": []
        }
      ],
      "actions": [
        {
          "type": {
            "inverted": false,
            "value": "Delete"
          },
          "parameters": [
            "bomb",
            "bomb"
          ],
          "subInstructions": []
        }
      ],
      "events": []
    },
    {
      "disabled": false,
      "folded": false,
      "type": "BuiltinCommonInstructions::Standard",
      "conditions": [],
      "actions": [],
      "events": []
    },
    {
      "disabled": false,
      "folded": false,
      "type": "BuiltinCommonInstructions::Standard",
      "conditions": [],
      "actions": [],
      "events": []
    },
    {
      "disabled": false,
      "folded": false,
      "type": "BuiltinCommonInstructions::Standard",
      "conditions": [],
      "actions": [],
      "events": []
    },
    {
      "disabled": false,
      "folded": false,
      "type": "BuiltinCommonInstructions::Standard",
      "conditions": [],
      "actions": [],
      "events": []
    },
    {
      "disabled": false,
      "folded": false,
      "type": "BuiltinCommonInstructions::Standard",
      "conditions": [],
      "actions": [],
      "events": []
    },
    {
      "disabled": false,
      "folded": false,
      "type": "BuiltinCommonInstructions::Standard",
      "conditions": [],
      "actions": [],
      "events": []
    },
    {
      "disabled": false,
      "folded": false,
      "type": "BuiltinCommonInstructions::ForEach",
      "object": "pique",
      "conditions": [
        {
          "type": {
            "inverted": false,
            "value": "FlippedX"
          },
          "parameters": [
            "mod"
          ],
          "subInstructions": []
        },
        {
          "type": {
            "inverted": false,
            "value": "CollisionNP"
          },
          "parameters": [
            "pique",
            "mod",
            "",
            "",
            ""
          ],
          "subInstructions": []
        },
        {
          "type": {
            "inverted": false,
            "value": "Animation"
          },
          "parameters": [
            "mod",
            "=",
            "2"
          ],
          "subInstructions": []
        }
      ],
      "actions": [
        {
          "type": {
            "inverted": false,
            "value": "Arreter"
          },
          "parameters": [
            "pique"
          ],
          "subInstructions": []
        },
        {
          "type": {
            "inverted": false,
            "value": "AddForceXY"
          },
          "parameters": [
            "pique",
            "-200",
            "0",
            "1"
          ],
          "subInstructions": []
        }
      ],
      "events": []
    },
    {
      "disabled": false,
      "folded": false,
      "type": "BuiltinCommonInstructions::ForEach",
      "object": "pique",
      "conditions": [
        {
          "type": {
            "inverted": true,
            "value": "FlippedX"
          },
          "parameters": [
            "mod"
          ],
          "subInstructions": []
        },
        {
          "type": {
            "inverted": false,
            "value": "CollisionNP"
          },
          "parameters": [
            "pique",
            "mod",
            "",
            "",
            ""
          ],
          "subInstructions": []
        },
        {
          "type": {
            "inverted": false,
            "value": "Animation"
          },
          "parameters": [
            "mod",
            "=",
            "2"
          ],
          "subInstructions": []
        }
      ],
      "actions": [
        {
          "type": {
            "inverted": false,
            "value": "Arreter"
          },
          "parameters": [
            "pique"
          ],
          "subInstructions": []
        },
        {
          "type": {
            "inverted": false,
            "value": "AddForceXY"
          },
          "parameters": [
            "pique",
            "200",
            "0",
            "1"
          ],
          "subInstructions": []
        }
      ],
      "events": []
    },
    {
      "disabled": true,
      "folded": false,
      "type": "BuiltinCommonInstructions::ForEach",
      "object": "pique",
      "conditions": [
        {
          "type": {
            "inverted": false,
            "value": "CollisionNP"
          },
          "parameters": [
            "pique",
            "mod",
            "",
            "",
            "yes"
          ],
          "subInstructions": []
        }
      ],
      "actions": [
        {
          "type": {
            "inverted": false,
            "value": "ModVarObjet"
          },
          "parameters": [
            "pique",
            "overcol",
            "=",
            "1"
          ],
          "subInstructions": []
        }
      ],
      "events": []
    },
    {
      "disabled": true,
      "folded": false,
      "type": "BuiltinCommonInstructions::ForEach",
      "object": "pique",
      "conditions": [
        {
          "type": {
            "inverted": false,
            "value": "CollisionNP"
          },
          "parameters": [
            "pique",
            "mod",
            "",
            "",
            "no"
          ],
          "subInstructions": []
        }
      ],
      "actions": [
        {
          "type": {
            "inverted": false,
            "value": "ModVarObjet"
          },
          "parameters": [
            "pique",
            "overcol",
            "=",
            "2"
          ],
          "subInstructions": []
        }
      ],
      "events": []
    },
    {
      "disabled": true,
      "folded": false,
      "type": "BuiltinCommonInstructions::ForEach",
      "object": "pique",
      "conditions": [
        {
          "type": {
            "inverted": false,
            "value": "VarObjet"
          },
          "parameters": [
            "pique",
            "overcol",
            "=",
            "2"
          ],
          "subInstructions": []
        }
      ],
      "actions": [
        {
          "type": {
            "inverted": false,
            "value": "Delete"
          },
          "parameters": [
            "pique",
            ""
          ],
          "subInstructions": []
        }
      ],
      "events": []
    },
    {
      "disabled": false,
      "folded": false,
      "type": "BuiltinCommonInstructions::Standard",
      "conditions": [],
      "actions": [],
      "events": []
    },
    {
      "disabled": false,
      "folded": false,
      "type": "BuiltinCommonInstructions::Standard",
      "conditions": [],
      "actions": [],
      "events": []
    },
    {
      "disabled": false,
      "folded": false,
      "type": "BuiltinCommonInstructions::Standard",
      "conditions": [],
      "actions": [],
      "events": []
    },
    {
      "disabled": false,
      "folded": false,
      "type": "BuiltinCommonInstructions::Standard",
      "conditions": [],
      "actions": [],
      "events": []
    },
    {
      "disabled": false,
      "folded": false,
      "type": "BuiltinCommonInstructions::Standard",
      "conditions": [],
      "actions": [],
      "events": []
    },
    {
      "disabled": false,
      "folded": false,
      "type": "BuiltinCommonInstructions::Standard",
      "conditions": [],
      "actions": [],
      "events": []
    },
    {
      "disabled": false,
      "folded": false,
      "type": "BuiltinCommonInstructions::Standard",
      "conditions": [],
      "actions": [],
      "events": []
    },
    {
      "disabled": false,
      "folded": false,
      "type": "BuiltinCommonInstructions::Standard",
      "conditions": [],
      "actions": [],
      "events": []
    },
    {
      "disabled": false,
      "folded": false,
      "type": "BuiltinCommonInstructions::Standard",
      "conditions": [],
      "actions": [],
      "events": []
    }
  ]
}